{"assets":{"wf_act_match_to_sshot_64_a_2_0":{"offsets":{"left":32,"top":34},"sprite":{"left":34,"top":61,"width":64,"height":51}},"wf_act_match_to_sshot_64_a_2_1":{"offsets":{"left":32,"top":34},"sprite":{"left":0,"top":112,"width":64,"height":51}},"wf_act_match_to_sshot_64_a_2_2":{"offsets":{"left":32,"top":34},"sprite":{"left":64,"top":112,"width":64,"height":51}},"wf_act_match_to_sshot_64_a_2_3":{"offsets":{"left":32,"top":34},"sprite":{"left":0,"top":163,"width":64,"height":51}},"wf_act_match_to_sshot_64_a_2_4":{"offsets":{"left":32,"top":34},"sprite":{"left":64,"top":163,"width":64,"height":51}},"wf_act_match_to_sshot_64_a_2_5":{"offsets":{"left":32,"top":34},"sprite":{"left":0,"top":214,"width":64,"height":51}},"wf_act_match_to_sshot_64_a_2_6":{"offsets":{"left":32,"top":34},"sprite":{"left":64,"top":214,"width":64,"height":51}},"wf_act_match_to_sshot_64_a_2_7":{"offsets":{"left":32,"top":34},"sprite":{"left":0,"top":265,"width":64,"height":51}},"wf_act_match_to_sshot_64_a_2_8":{"offsets":{"left":32,"top":34},"sprite":{"left":64,"top":265,"width":64,"height":51}},"wf_act_match_to_sshot_32_a_2_0":{"offsets":{"left":16,"top":18},"sprite":{"left":30,"top":0,"width":32,"height":27}},"wf_act_match_to_sshot_32_a_2_1":{"offsets":{"left":16,"top":18},"sprite":{"left":62,"top":0,"width":32,"height":27}},"wf_act_match_to_sshot_32_a_2_2":{"offsets":{"left":16,"top":18},"sprite":{"left":94,"top":0,"width":32,"height":27}},"wf_act_match_to_sshot_32_a_2_3":{"offsets":{"left":18,"top":18},"sprite":{"left":0,"top":30,"width":34,"height":31}},"wf_act_match_to_sshot_32_a_2_4":{"offsets":{"left":18,"top":18},"sprite":{"left":34,"top":30,"width":34,"height":31}},"wf_act_match_to_sshot_32_a_2_5":{"offsets":{"left":18,"top":18},"sprite":{"left":68,"top":30,"width":34,"height":31}},"wf_act_match_to_sshot_32_a_2_6":{"offsets":{"left":18,"top":18},"sprite":{"left":0,"top":61,"width":34,"height":31}},"wf_act_match_to_sshot_icon_a":{"offsets":{"left":15,"top":15},"sprite":{"left":0,"top":0,"width":30,"height":30}},"wf_act_match_to_sshot_64_a_6_0":{"offsets":{"left":32,"top":34},"source":"wf_act_match_to_sshot_64_a_2_0","flipH":1},"wf_act_match_to_sshot_64_a_6_1":{"offsets":{"left":32,"top":34},"source":"wf_act_match_to_sshot_64_a_2_1","flipH":1},"wf_act_match_to_sshot_64_a_6_2":{"offsets":{"left":32,"top":34},"source":"wf_act_match_to_sshot_64_a_2_2","flipH":1},"wf_act_match_to_sshot_64_a_6_3":{"offsets":{"left":32,"top":34},"source":"wf_act_match_to_sshot_64_a_2_3","flipH":1},"wf_act_match_to_sshot_64_a_6_4":{"offsets":{"left":32,"top":34},"source":"wf_act_match_to_sshot_64_a_2_4","flipH":1},"wf_act_match_to_sshot_64_a_6_5":{"offsets":{"left":32,"top":34},"source":"wf_act_match_to_sshot_64_a_2_5","flipH":1},"wf_act_match_to_sshot_64_a_6_6":{"offsets":{"left":32,"top":34},"source":"wf_act_match_to_sshot_64_a_2_6","flipH":1},"wf_act_match_to_sshot_64_a_6_7":{"offsets":{"left":32,"top":34},"source":"wf_act_match_to_sshot_64_a_2_7","flipH":1},"wf_act_match_to_sshot_64_a_6_8":{"offsets":{"left":32,"top":34},"source":"wf_act_match_to_sshot_64_a_2_8","flipH":1},"wf_act_match_to_sshot_32_a_6_0":{"offsets":{"left":16,"top":18},"source":"wf_act_match_to_sshot_32_a_2_0","flipH":1},"wf_act_match_to_sshot_32_a_6_1":{"offsets":{"left":16,"top":18},"source":"wf_act_match_to_sshot_32_a_2_1","flipH":1},"wf_act_match_to_sshot_32_a_6_2":{"offsets":{"left":16,"top":18},"source":"wf_act_match_to_sshot_32_a_2_2","flipH":1},"wf_act_match_to_sshot_32_a_6_3":{"offsets":{"left":18,"top":18},"source":"wf_act_match_to_sshot_32_a_2_3","flipH":1},"wf_act_match_to_sshot_32_a_6_4":{"offsets":{"left":18,"top":18},"source":"wf_act_match_to_sshot_32_a_2_4","flipH":1},"wf_act_match_to_sshot_32_a_6_5":{"offsets":{"left":18,"top":18},"source":"wf_act_match_to_sshot_32_a_2_5","flipH":1},"wf_act_match_to_sshot_32_a_6_6":{"offsets":{"left":18,"top":18},"source":"wf_act_match_to_sshot_32_a_2_6","flipH":1}},"visualization":{"type":"furniture_animated","layerCount":1,"layers":{},"directions":{"2":{},"6":{}},"colors":{},"animations":{"0":{"layers":{"0":{"sequences":[[{"frame":0},{"frame":1},{"frame":2}]],"loopCount":0,"frameRepeat":4}}},"1":{"layers":{"0":{"sequences":[[{"frame":0},{"frame":1},{"frame":2}]],"loopCount":0,"frameRepeat":4}}},"100":{"transitionTo":1,"layers":{"0":{"sequences":[[{"frame":3},{"frame":4},{"frame":5},{"frame":6},{"frame":7},{"frame":8},{"frame":7},{"frame":8},{"frame":7},{"frame":8}]],"frameRepeat":3}}},"101":{"transitionTo":0,"layers":{"0":{"sequences":[[{"frame":3},{"frame":4},{"frame":5},{"frame":6},{"frame":7},{"frame":8},{"frame":7},{"frame":8},{"frame":7},{"frame":8}]],"frameRepeat":3}}}}},"logic":{"type":"furniture_multistate","dimensions":[1.0,1.0,0.65],"directions":[90,270],"particlesystems":[]}}