{"sh_std_ch_2110_7_0":{"offset":"-10,24","left":"0","top":"60","width":"13","height":"15"},"sh_std_rs_2110_7_0":{"offset":"-22,23","link":"sh_wlk_rs_2110_7_2"},"sh_std_ls_2110_7_0":{"offset":"-8,23","left":"51","top":"20","width":"3","height":"12"},"sh_std_rs_2110_3_0":{"offset":"-7,23","left":"43","top":"32","width":"3","height":"13"},"sh_std_ls_2110_3_0":{"offset":"-21,23","left":"35","top":"32","width":"3","height":"13"},"sh_std_ch_2110_3_0":{"offset":"-9,24","left":"107","top":"45","width":"13","height":"15"},"sh_std_ch_2110_2_0":{"offset":"-10,24","left":"96","top":"60","width":"13","height":"16"},"sh_std_ls_2110_2_0":{"offset":"-20,23","left":"94","top":"9","width":"3","height":"11"},"sh_std_rs_2110_2_0":{"offset":"-8,22","left":"38","top":"32","width":"5","height":"13"},"sh_std_ls_2110_1_0":{"offset":"-14,21","link":"sh_wlk_ls_2110_1_2"},"sh_std_ch_2110_1_0":{"offset":"-12,24","left":"76","top":"45","width":"10","height":"14"},"sh_std_rs_2110_1_0":{"offset":"-14,21","link":"sh_wlk_ls_2110_1_2"},"sh_std_ch_2110_0_0":{"offset":"-10,25","left":"83","top":"60","width":"13","height":"16"},"sh_std_ls_2110_0_0":{"offset":"-9,23","left":"92","top":"9","width":"2","height":"11"},"sh_std_rs_2110_0_0":{"offset":"-19,22","left":"54","top":"20","width":"4","height":"12"},"sh_wlk_ls_2110_0_0":{"offset":"-8,23","left":"105","top":"9","width":"3","height":"11"},"sh_wlk_ls_2110_0_1":{"offset":"-10,24","left":"52","top":"0","width":"3","height":"7"},"sh_wlk_ls_2110_0_2":{"offset":"-8,23","left":"108","top":"9","width":"4","height":"11"},"sh_wlk_ls_2110_0_3":{"offset":"-7,22","left":"66","top":"9","width":"4","height":"10"},"sh_wlk_rs_2110_0_0":{"offset":"-19,22","left":"96","top":"20","width":"5","height":"12"},"sh_wlk_rs_2110_0_1":{"offset":"-17,23","left":"4","top":"45","width":"6","height":"13"},"sh_wlk_rs_2110_0_2":{"offset":"-19,22","left":"101","top":"20","width":"5","height":"12"},"sh_wlk_rs_2110_0_3":{"offset":"-19,22","left":"3","top":"20","width":"7","height":"11"},"sh_wlk_ls_2110_1_0":{"offset":"-14,21","link":"sh_wlk_ls_2110_1_2"},"sh_wlk_ls_2110_1_1":{"offset":"-17,20","left":"21","top":"9","width":"5","height":"9"},"sh_wlk_ls_2110_1_2":{"offset":"-14,21","left":"112","top":"9","width":"4","height":"11"},"sh_wlk_ls_2110_1_3":{"offset":"-9,21","left":"116","top":"9","width":"9","height":"11"},"sh_wlk_rs_2110_1_0":{"offset":"-14,22","left":"106","top":"20","width":"5","height":"12"},"sh_wlk_rs_2110_1_1":{"offset":"-11,21","left":"10","top":"20","width":"5","height":"11"},"sh_wlk_rs_2110_1_2":{"offset":"-13,22","left":"111","top":"20","width":"5","height":"12"},"sh_wlk_rs_2110_1_3":{"offset":"-14,20","left":"74","top":"9","width":"8","height":"10"},"sh_wlk_ls_2110_2_0":{"offset":"-20,23","link":"sh_std_ls_2110_2_0"},"sh_wlk_ls_2110_2_1":{"offset":"-20,22","left":"70","top":"9","width":"4","height":"10"},"sh_wlk_ls_2110_2_2":{"offset":"-20,23","link":"sh_std_ls_2110_2_0"},"sh_wlk_ls_2110_2_3":{"offset":"-19,22","left":"55","top":"0","width":"3","height":"7"},"sh_wlk_rs_2110_2_0":{"offset":"-8,21","left":"116","top":"20","width":"5","height":"12"},"sh_wlk_rs_2110_2_1":{"offset":"-6,22","left":"0","top":"32","width":"7","height":"12"},"sh_wlk_rs_2110_2_2":{"offset":"-8,21","left":"7","top":"32","width":"6","height":"12"},"sh_wlk_rs_2110_2_3":{"offset":"-7,22","left":"10","top":"45","width":"7","height":"13"},"sh_wlk_rs_2110_3_0":{"offset":"-7,23","link":"sh_std_rs_2110_3_0"},"sh_wlk_rs_2110_3_1":{"offset":"-7,23","left":"13","top":"32","width":"3","height":"12"},"sh_wlk_rs_2110_3_2":{"offset":"-7,23","link":"sh_std_rs_2110_3_0"},"sh_wlk_rs_2110_3_3":{"offset":"-7,23","left":"16","top":"32","width":"4","height":"12"},"sh_wlk_ls_2110_3_0":{"offset":"-21,23","link":"sh_std_ls_2110_3_0"},"sh_wlk_ls_2110_3_1":{"offset":"-20,23","left":"89","top":"20","width":"4","height":"12"},"sh_wlk_ls_2110_3_2":{"offset":"-21,23","link":"sh_std_ls_2110_3_0"},"sh_wlk_ls_2110_3_3":{"offset":"-21,23","left":"93","top":"20","width":"3","height":"12"},"sh_wlk_rs_2110_7_0":{"offset":"-22,23","link":"sh_wlk_rs_2110_7_2"},"sh_wlk_rs_2110_7_1":{"offset":"-21,23","left":"20","top":"32","width":"4","height":"12"},"sh_wlk_rs_2110_7_2":{"offset":"-22,23","left":"24","top":"32","width":"3","height":"12"},"sh_wlk_rs_2110_7_3":{"offset":"-22,23","left":"15","top":"20","width":"3","height":"11"},"sh_wlk_ls_2110_7_0":{"offset":"-8,23","link":"sh_std_ls_2110_7_0"},"sh_wlk_ls_2110_7_1":{"offset":"-8,23","left":"0","top":"20","width":"3","height":"11"},"sh_wlk_ls_2110_7_2":{"offset":"-8,23","link":"sh_std_ls_2110_7_0"},"sh_wlk_ls_2110_7_3":{"offset":"-8,24","left":"0","top":"45","width":"4","height":"13"},"sh_wav_ls_2110_0_0":{"offset":"-5,32","left":"46","top":"32","width":"8","height":"13"},"sh_wav_ls_2110_0_1":{"offset":"-4,32","left":"54","top":"32","width":"8","height":"13"},"sh_wav_ls_2110_1_0":{"offset":"-16,32","left":"62","top":"32","width":"5","height":"13"},"sh_wav_ls_2110_1_1":{"offset":"-17,32","left":"58","top":"20","width":"5","height":"12"},"sh_wav_ls_2110_2_0":{"offset":"-18,30","left":"67","top":"32","width":"7","height":"13"},"sh_wav_ls_2110_2_1":{"offset":"-18,32","left":"13","top":"60","width":"9","height":"15"},"sh_wav_ls_2110_3_0":{"offset":"-20,31","left":"74","top":"32","width":"8","height":"13"},"sh_wav_ls_2110_3_1":{"offset":"-20,31","left":"82","top":"32","width":"9","height":"13"},"sh_wav_ls_2110_4_0":{"offset":"-20,30","left":"91","top":"32","width":"8","height":"13"},"sh_wav_ls_2110_4_1":{"offset":"-20,30","left":"99","top":"32","width":"9","height":"13"},"sh_wav_ls_2110_5_0":{"offset":"-11,30","left":"97","top":"9","width":"8","height":"11"},"sh_wav_ls_2110_5_1":{"offset":"-12,31","left":"63","top":"20","width":"7","height":"12"},"sh_wav_ls_2110_6_0":{"offset":"-3,29","left":"70","top":"20","width":"10","height":"12"},"sh_wav_ls_2110_6_1":{"offset":"-3,29","left":"80","top":"20","width":"9","height":"12"},"sh_wav_ls_2110_7_0":{"offset":"-5,31","left":"108","top":"32","width":"8","height":"13"},"sh_wav_ls_2110_7_1":{"offset":"-4,31","left":"116","top":"32","width":"9","height":"13"},"sh_sit_ls_2110_0_0":{"offset":"-9,23","left":"90","top":"9","width":"2","height":"11"},"sh_sit_rs_2110_0_0":{"offset":"-17,22","left":"64","top":"45","width":"6","height":"14"},"sh_sit_ls_2110_2_0":{"offset":"-19,22","left":"62","top":"9","width":"4","height":"10"},"sh_sit_rs_2110_2_0":{"offset":"-8,22","left":"70","top":"45","width":"6","height":"14"},"sh_lay_ls_2110_2_0":{"offset":"-6,11","left":"34","top":"0","width":"12","height":"6"},"sh_lay_ch_2110_2_0":{"offset":"1,11","left":"44","top":"45","width":"20","height":"14"},"sh_lay_rs_2110_2_0":{"offset":"1,7","left":"11","top":"9","width":"10","height":"9"},"sh_crr_rs_2110_0_0":{"offset":"-19,21","left":"49","top":"9","width":"8","height":"10"},"sh_crr_ls_2110_0_0":{"offset":"-8,23","left":"91","top":"0","width":"3","height":"9"},"sh_crr_rs_2110_1_0":{"offset":"-14,21","left":"110","top":"0","width":"8","height":"9"},"sh_crr_ls_2110_1_0":{"offset":"-14,21","left":"94","top":"0","width":"8","height":"9"},"sh_crr_rs_2110_2_0":{"offset":"-9,22","left":"27","top":"32","width":"8","height":"13"},"sh_crr_ls_2110_2_0":{"offset":"-20,22","left":"102","top":"0","width":"5","height":"9"},"sh_crr_rs_2110_3_0":{"offset":"-7,23","left":"86","top":"9","width":"4","height":"11"},"sh_crr_ls_2110_3_0":{"offset":"-20,23","left":"82","top":"9","width":"4","height":"11"},"sh_crr_rs_2110_4_0":{"offset":"-8,23","left":"57","top":"9","width":"5","height":"10"},"sh_crr_rs_2110_5_0":{"offset":"-9,22","left":"0","top":"9","width":"8","height":"9"},"sh_crr_rs_2110_6_0":{"offset":"-20,25","left":"47","top":"20","width":"4","height":"12"},"sh_crr_rs_2110_7_0":{"offset":"-22,22","left":"8","top":"9","width":"3","height":"9"},"sh_crr_ls_2110_7_0":{"offset":"-8,22","left":"107","top":"0","width":"3","height":"9"},"sh_drk_rs_2110_0_0":{"offset":"-19,26","left":"58","top":"0","width":"9","height":"8"},"sh_drk_rs_2110_1_0":{"offset":"-15,24","left":"0","top":"0","width":"12","height":"6"},"sh_drk_rs_2110_2_0":{"offset":"-9,23","left":"67","top":"0","width":"11","height":"8"},"sh_drk_rs_2110_3_0":{"offset":"-7,23","left":"78","top":"0","width":"7","height":"8"},"sh_drk_rs_2110_4_0":{"offset":"-5,24","left":"46","top":"0","width":"6","height":"7"},"sh_drk_rs_2110_5_0":{"offset":"-7,24","left":"12","top":"0","width":"11","height":"6"},"sh_drk_rs_2110_6_0":{"offset":"-11,25","left":"23","top":"0","width":"11","height":"6"},"sh_drk_rs_2110_7_0":{"offset":"-19,26","left":"85","top":"0","width":"6","height":"8"},"h_std_ls_2110_0_0":{"offset":"-17,45","left":"108","top":"77","width":"5","height":"20"},"h_std_ch_2110_0_0":{"offset":"-20,48","left":"75","top":"247","width":"24","height":"32"},"h_std_rs_2110_0_0":{"offset":"-37,43","left":"46","top":"194","width":"10","height":"26"},"h_std_ls_2110_1_0":{"offset":"-28,42","left":"94","top":"119","width":"7","height":"24"},"h_std_ch_2110_1_0":{"offset":"-24,48","left":"38","top":"220","width":"19","height":"27"},"h_std_rs_2110_1_0":{"offset":"-28,42","left":"109","top":"119","width":"7","height":"24"},"h_std_ls_2110_2_0":{"offset":"-43,47","left":"41","top":"97","width":"5","height":"21"},"h_std_ch_2110_2_0":{"offset":"-22,49","left":"99","top":"247","width":"25","height":"32"},"h_std_rs_2110_2_0":{"offset":"-19,44","left":"116","top":"119","width":"8","height":"24"},"h_std_ch_2110_3_0":{"offset":"-22,50","left":"52","top":"247","width":"23","height":"30"},"h_std_rs_2110_3_0":{"offset":"-17,48","left":"56","top":"194","width":"8","height":"26"},"h_std_ls_2110_3_0":{"offset":"-42,48","left":"38","top":"194","width":"8","height":"26"},"h_std_rs_2110_7_0":{"offset":"-43,44","left":"0","top":"143","width":"7","height":"24"},"h_std_ls_2110_7_0":{"offset":"-17,44","left":"101","top":"119","width":"8","height":"24"},"h_std_ch_2110_7_0":{"offset":"-22,46","left":"10","top":"247","width":"23","height":"28"},"h_wlk_ls_2110_0_0":{"offset":"-17,45","left":"113","top":"77","width":"5","height":"20"},"h_wlk_ls_2110_0_1":{"offset":"-18,47","left":"36","top":"77","width":"6","height":"18"},"h_wlk_ls_2110_0_2":{"offset":"-17,45","left":"118","top":"77","width":"5","height":"20"},"h_wlk_ls_2110_0_3":{"offset":"-14,45","left":"46","top":"97","width":"8","height":"21"},"h_wlk_rs_2110_0_0":{"offset":"-36,43","left":"41","top":"119","width":"10","height":"23"},"h_wlk_rs_2110_0_1":{"offset":"-34,42","left":"51","top":"119","width":"11","height":"23"},"h_wlk_rs_2110_0_2":{"offset":"-36,44","left":"114","top":"194","width":"10","height":"26"},"h_wlk_rs_2110_0_3":{"offset":"-36,42","left":"0","top":"119","width":"14","height":"22"},"h_wlk_ls_2110_1_0":{"offset":"-28,42","left":"45","top":"143","width":"7","height":"24"},"h_wlk_ls_2110_1_1":{"offset":"-28,42","link":"h_wlk_ls_2110_1_2"},"h_wlk_ls_2110_1_2":{"offset":"-28,42","left":"52","top":"143","width":"7","height":"24"},"h_wlk_ls_2110_1_3":{"offset":"-21,40","left":"42","top":"77","width":"3","height":"18"},"h_wlk_rs_2110_1_0":{"offset":"-27,42","left":"62","top":"119","width":"8","height":"23"},"h_wlk_rs_2110_1_1":{"offset":"-21,42","left":"71","top":"97","width":"13","height":"21"},"h_wlk_rs_2110_1_2":{"offset":"-27,42","left":"70","top":"119","width":"8","height":"23"},"h_wlk_rs_2110_1_3":{"offset":"-28,40","left":"0","top":"97","width":"13","height":"20"},"h_wlk_ls_2110_2_0":{"offset":"-43,47","left":"54","top":"97","width":"5","height":"21"},"h_wlk_ls_2110_2_1":{"offset":"-44,46","left":"59","top":"97","width":"7","height":"21"},"h_wlk_ls_2110_2_2":{"offset":"-43,47","left":"66","top":"97","width":"5","height":"21"},"h_wlk_ls_2110_2_3":{"offset":"-42,46","left":"42","top":"20","width":"5","height":"12"},"h_wlk_rs_2110_2_0":{"offset":"-18,46","left":"0","top":"220","width":"10","height":"26"},"h_wlk_rs_2110_2_1":{"offset":"-15,45","left":"10","top":"220","width":"12","height":"26"},"h_wlk_rs_2110_2_2":{"offset":"-18,47","left":"33","top":"247","width":"9","height":"28"},"h_wlk_rs_2110_2_3":{"offset":"-19,46","left":"106","top":"220","width":"12","height":"27"},"h_wlk_rs_2110_3_0":{"offset":"-17,48","left":"22","top":"220","width":"8","height":"26"},"h_wlk_rs_2110_3_1":{"offset":"-17,48","left":"83","top":"143","width":"8","height":"24"},"h_wlk_rs_2110_3_2":{"offset":"-17,48","left":"30","top":"220","width":"8","height":"26"},"h_wlk_rs_2110_3_3":{"offset":"-17,48","left":"89","top":"168","width":"8","height":"25"},"h_wlk_ls_2110_3_0":{"offset":"-42,49","left":"90","top":"220","width":"8","height":"27"},"h_wlk_ls_2110_3_1":{"offset":"-42,48","left":"106","top":"194","width":"8","height":"26"},"h_wlk_ls_2110_3_2":{"offset":"-42,49","left":"98","top":"220","width":"8","height":"27"},"h_wlk_ls_2110_3_3":{"offset":"-42,48","left":"59","top":"143","width":"8","height":"24"},"h_wlk_rs_2110_7_0":{"offset":"-43,44","left":"91","top":"143","width":"7","height":"24"},"h_wlk_rs_2110_7_1":{"offset":"-42,44","left":"98","top":"143","width":"8","height":"24"},"h_wlk_rs_2110_7_2":{"offset":"-42,45","left":"97","top":"168","width":"8","height":"25"},"h_wlk_rs_2110_7_3":{"offset":"-42,44","left":"14","top":"119","width":"8","height":"22"},"h_wlk_ls_2110_7_0":{"offset":"-17,45","left":"73","top":"168","width":"8","height":"25"},"h_wlk_ls_2110_7_1":{"offset":"-17,44","left":"67","top":"143","width":"8","height":"24"},"h_wlk_ls_2110_7_2":{"offset":"-17,45","left":"81","top":"168","width":"8","height":"25"},"h_wlk_ls_2110_7_3":{"offset":"-17,44","left":"75","top":"143","width":"8","height":"24"},"h_wav_ls_2110_0_0":{"offset":"-12,63","left":"7","top":"143","width":"12","height":"24"},"h_wav_ls_2110_0_1":{"offset":"-9,63","left":"19","top":"143","width":"15","height":"24"},"h_wav_ls_2110_1_0":{"offset":"-32,66","left":"34","top":"143","width":"11","height":"24"},"h_wav_ls_2110_1_1":{"offset":"-33,66","left":"64","top":"194","width":"11","height":"26"},"h_wav_ls_2110_2_0":{"offset":"-41,64","left":"111","top":"143","width":"13","height":"25"},"h_wav_ls_2110_2_1":{"offset":"-41,64","left":"0","top":"168","width":"15","height":"25"},"h_wav_ls_2110_3_0":{"offset":"-43,62","left":"15","top":"168","width":"13","height":"25"},"h_wav_ls_2110_3_1":{"offset":"-43,62","left":"28","top":"168","width":"15","height":"25"},"h_wav_ls_2110_4_0":{"offset":"-42,60","left":"43","top":"168","width":"16","height":"25"},"h_wav_ls_2110_4_1":{"offset":"-42,60","left":"59","top":"168","width":"14","height":"25"},"h_wav_ls_2110_5_0":{"offset":"-22,62","left":"75","top":"194","width":"16","height":"26"},"h_wav_ls_2110_5_1":{"offset":"-23,62","left":"91","top":"194","width":"15","height":"26"},"h_wav_ls_2110_6_0":{"offset":"-11,57","left":"22","top":"119","width":"19","height":"23"},"h_wav_ls_2110_6_1":{"offset":"-9,56","left":"103","top":"97","width":"21","height":"22"},"h_wav_ls_2110_7_0":{"offset":"-12,62","left":"57","top":"220","width":"15","height":"27"},"h_wav_ls_2110_7_1":{"offset":"-9,62","left":"72","top":"220","width":"18","height":"27"},"h_crr_ls_2110_0_0":{"offset":"-17,45","left":"109","top":"60","width":"4","height":"17"},"h_crr_rs_2110_0_0":{"offset":"-36,43","left":"24","top":"97","width":"17","height":"21"},"h_crr_ls_2110_1_0":{"offset":"-27,42","left":"22","top":"60","width":"15","height":"16"},"h_crr_rs_2110_1_0":{"offset":"-28,42","left":"21","top":"77","width":"15","height":"18"},"h_crr_ls_2110_2_0":{"offset":"-43,47","left":"13","top":"97","width":"11","height":"21"},"h_crr_rs_2110_2_0":{"offset":"-19,47","left":"105","top":"168","width":"14","height":"26"},"h_crr_ls_2110_3_0":{"offset":"-41,48","left":"78","top":"119","width":"8","height":"24"},"h_crr_rs_2110_3_0":{"offset":"-17,48","left":"86","top":"119","width":"8","height":"24"},"h_crr_rs_2110_4_0":{"offset":"-13,45","left":"45","top":"77","width":"12","height":"19"},"h_crr_rs_2110_5_0":{"offset":"-24,47","left":"84","top":"97","width":"14","height":"22"},"h_crr_rs_2110_6_0":{"offset":"-45,45","left":"57","top":"77","width":"5","height":"19"},"h_crr_ls_2110_7_0":{"offset":"-17,45","left":"94","top":"77","width":"7","height":"20"},"h_crr_rs_2110_7_0":{"offset":"-43,45","left":"101","top":"77","width":"7","height":"20"},"h_sit_ls_2110_0_0":{"offset":"-17,45","left":"98","top":"97","width":"5","height":"22"},"h_sit_rs_2110_0_0":{"offset":"-37,43","left":"0","top":"247","width":"10","height":"28"},"h_sit_ls_2110_2_0":{"offset":"-43,45","left":"106","top":"143","width":"5","height":"25"},"h_sit_rs_2110_2_0":{"offset":"-18,47","left":"42","top":"247","width":"10","height":"30"},"h_lay_ls_2110_2_0":{"offset":"-13,23","left":"59","top":"60","width":"24","height":"16"},"h_lay_ch_2110_2_0":{"offset":"3,23","left":"0","top":"194","width":"38","height":"26"},"h_lay_rs_2110_2_0":{"offset":"4,15","left":"0","top":"77","width":"21","height":"17"},"h_drk_rs_2110_0_0":{"offset":"-36,53","left":"62","top":"77","width":"17","height":"19"},"h_drk_rs_2110_1_0":{"offset":"-28,45","left":"26","top":"9","width":"23","height":"10"},"h_drk_rs_2110_2_0":{"offset":"-24,44","left":"86","top":"45","width":"21","height":"15"},"h_drk_rs_2110_3_0":{"offset":"-18,49","left":"79","top":"77","width":"15","height":"19"},"h_drk_rs_2110_4_0":{"offset":"-11,47","left":"37","top":"60","width":"13","height":"16"},"h_drk_rs_2110_5_0":{"offset":"-10,47","left":"18","top":"20","width":"24","height":"12"},"h_drk_rs_2110_6_0":{"offset":"-19,51","left":"17","top":"45","width":"27","height":"14"},"h_drk_rs_2110_7_0":{"offset":"-39,49","left":"50","top":"60","width":"9","height":"16"},"manifest":{},"Shirt_F_Schoolshirt":{}}