{"assets":{"window_70s_narrow_64_a_2_0":{"offsets":{"left":32,"top":56},"sprite":{"left":35,"top":60,"width":65,"height":112}},"window_70s_narrow_64_b_2_0":{"offsets":{"left":21,"top":24},"sprite":{"left":0,"top":0,"width":1,"height":1}},"window_70s_narrow_64_b_2_1":{"offsets":{"left":21,"top":40},"sprite":{"left":0,"top":60,"width":35,"height":77}},"window_70s_narrow_64_2_mask":{"offsets":{"left":20,"top":26},"sprite":{"left":48,"top":0,"width":30,"height":60}},"window_70s_narrow_64_a_4_0":{"offsets":{"left":32,"top":56},"source":"window_70s_narrow_64_a_2_0","flipH":1},"window_70s_narrow_64_b_4_0":{"offsets":{"left":21,"top":24},"source":"window_70s_narrow_64_b_2_0","flipH":1},"window_70s_narrow_64_b_4_1":{"offsets":{"left":21,"top":40},"source":"window_70s_narrow_64_b_2_1","flipH":1},"window_70s_narrow_64_4_mask":{"offsets":{"left":20,"top":26},"source":"window_70s_narrow_64_2_mask","flipH":1},"window_70s_narrow_32_a_2_0":{"offsets":{"left":16,"top":28},"sprite":{"left":78,"top":0,"width":33,"height":56}},"window_70s_narrow_32_b_2_0":{"offsets":{"left":10,"top":12},"source":"window_70s_narrow_64_b_2_0"},"window_70s_narrow_32_b_2_1":{"offsets":{"left":10,"top":21},"sprite":{"left":30,"top":0,"width":18,"height":39}},"window_70s_narrow_32_2_mask":{"offsets":{"left":9,"top":13},"sprite":{"left":1,"top":0,"width":14,"height":29}},"window_70s_narrow_32_a_4_0":{"offsets":{"left":16,"top":28},"source":"window_70s_narrow_32_a_2_0","flipH":1},"window_70s_narrow_32_b_4_0":{"offsets":{"left":10,"top":12},"source":"window_70s_narrow_32_b_2_0","flipH":1},"window_70s_narrow_32_b_4_1":{"offsets":{"left":10,"top":21},"source":"window_70s_narrow_32_b_2_1","flipH":1},"window_70s_narrow_32_4_mask":{"offsets":{"left":9,"top":13},"source":"window_70s_narrow_32_2_mask","flipH":1},"window_70s_narrow_icon_a":{"offsets":{"left":7,"top":10},"sprite":{"left":15,"top":0,"width":15,"height":20}}},"visualization":{"type":"furniture_animated","layerCount":2,"layers":{"0":{"z":"-3000"},"1":{"z":"-3000"}},"directions":{"2":{},"4":{}},"colors":{},"animations":{"0":{"layers":{"0":{"sequences":[[{"frame":0}]]},"1":{"sequences":[[{"frame":0}]]}}},"1":{"layers":{"1":{"sequences":[[{"frame":1}]]}}}}},"logic":{"type":"furniture_window","dimensions":[1.75,0.2,2.875],"directions":[90,180],"particlesystems":[]}}