{"h_lay_ea_3294_2_0":{"offset":"17,44","link":"h_lsp_ea_3294_2_0"},"h_lsp_ea_3294_2_0":{"offset":"-46,-115","left":"33","top":"38","width":"29","height":"32"},"h_std_ea_3294_3_0":{"offset":"-19,69","left":"30","top":"0","width":"32","height":"19"},"h_std_ea_3294_2_0":{"offset":"-19,71","left":"0","top":"38","width":"33","height":"23"},"h_std_ea_3294_1_0":{"offset":"-17,71","link":"h_spk_ea_3294_1_0"},"h_std_ea_3294_0_0":{"offset":"-22,69","link":"h_spk_ea_3294_0_0"},"h_spk_ea_3294_3_0":{"offset":"-19,70","link":"h_std_ea_3294_3_0"},"h_spk_ea_3294_2_0":{"offset":"-19,72","link":"h_std_ea_3294_2_0"},"h_spk_ea_3294_1_0":{"offset":"-17,72","left":"0","top":"19","width":"35","height":"19"},"h_spk_ea_3294_0_0":{"offset":"-22,70","left":"0","top":"0","width":"30","height":"17"},"manifest":{},"acc_eye_U_gold11":{}}