{"h_lay_he_3568_2_0":{"offset":"23,47","left":"13","top":"0","width":"19","height":"23"},"h_std_he_3568_0_0":{"offset":"-25,81","left":"0","top":"23","width":"26","height":"18"},"h_std_he_3568_1_0":{"offset":"-32,83","left":"0","top":"0","width":"13","height":"18"},"h_std_he_3568_2_0":{"offset":"-26,84","left":"32","top":"0","width":"22","height":"21"},"h_std_he_3568_3_0":{"offset":"-21,83","left":"26","top":"23","width":"28","height":"18"},"h_std_he_3568_7_0":{"offset":"-21,83","left":"0","top":"41","width":"28","height":"14"},"h_spk_he_3568_0_0":{"offset":"-25,82","link":"h_std_he_3568_0_0"},"h_spk_he_3568_1_0":{"offset":"-32,84","link":"h_std_he_3568_1_0"},"h_spk_he_3568_2_0":{"offset":"-26,85","link":"h_std_he_3568_2_0"},"h_spk_he_3568_3_0":{"offset":"-21,84","link":"h_std_he_3568_3_0"},"h_spk_he_3568_7_0":{"offset":"-21,84","link":"h_std_he_3568_7_0"},"manifest":{},"acc_head_U_gold13":{}}