{"assets":{"usva3_wallrug_64_a_2_0":{"offsets":{"left":34,"top":71},"sprite":{"left":67,"top":220,"width":68,"height":147}},"usva3_wallrug_64_a_2_1":{"offsets":{"left":34,"top":71},"sprite":{"left":135,"top":220,"width":68,"height":147}},"usva3_wallrug_64_a_2_2":{"offsets":{"left":34,"top":71},"sprite":{"left":0,"top":73,"width":67,"height":147}},"usva3_wallrug_64_a_4_0":{"offsets":{"left":33,"top":71},"sprite":{"left":67,"top":73,"width":67,"height":147}},"usva3_wallrug_64_a_4_1":{"offsets":{"left":33,"top":71},"sprite":{"left":134,"top":73,"width":67,"height":147}},"usva3_wallrug_64_a_4_2":{"offsets":{"left":33,"top":71},"sprite":{"left":0,"top":220,"width":67,"height":147}},"usva3_wallrug_32_a_2_0":{"offsets":{"left":16,"top":35},"sprite":{"left":13,"top":0,"width":33,"height":73}},"usva3_wallrug_32_a_2_1":{"offsets":{"left":16,"top":35},"sprite":{"left":46,"top":0,"width":33,"height":73}},"usva3_wallrug_32_a_2_2":{"offsets":{"left":16,"top":35},"sprite":{"left":79,"top":0,"width":33,"height":73}},"usva3_wallrug_32_a_4_0":{"offsets":{"left":16,"top":35},"sprite":{"left":112,"top":0,"width":33,"height":73}},"usva3_wallrug_32_a_4_1":{"offsets":{"left":16,"top":35},"sprite":{"left":145,"top":0,"width":33,"height":73}},"usva3_wallrug_32_a_4_2":{"offsets":{"left":16,"top":35},"sprite":{"left":178,"top":0,"width":33,"height":73}},"usva3_wallrug_icon_a":{"offsets":{"left":6,"top":15},"sprite":{"left":0,"top":0,"width":13,"height":30}}},"visualization":{"type":"furniture_animated","layerCount":1,"layers":{"0":{"z":"-3000"}},"directions":{"2":{},"4":{}},"colors":{},"animations":{"0":{"layers":{"0":{"sequences":[[{"frame":0}]]}}},"1":{"layers":{"0":{"sequences":[[{"frame":1}]]}}},"2":{"layers":{"0":{"sequences":[[{"frame":2}]]}}}}},"logic":{"type":"furniture_multistate","dimensions":[1.925,0.2,3.4063],"directions":[90,180],"particlesystems":[]}}