{"h_std_ea_3256_2_0":{"offset":"-22,63","left":"0","top":"48","width":"26","height":"17"},"h_std_ea_3256_1_0":{"offset":"-29,63","left":"10","top":"0","width":"17","height":"13"},"h_std_ea_3256_0_0":{"offset":"-38,65","left":"0","top":"0","width":"10","height":"13"},"h_std_ea_3256_3_0":{"offset":"-21,62","left":"0","top":"33","width":"24","height":"15"},"h_std_ea_3256_7_0":{"offset":"-20,58","left":"0","top":"65","width":"26","height":"4"},"h_lay_ea_3256_2_0":{"offset":"13,36","left":"0","top":"13","width":"22","height":"20"}}