{"assets":{"bb_counter_64_a_0_0":{"offsets":{"left":23,"top":30},"sprite":{"left":50,"top":540,"width":53,"height":43}},"bb_counter_64_b_0_0":{"offsets":{"left":55,"top":10},"sprite":{"left":0,"top":499,"width":47,"height":38}},"bb_counter_64_c_0_0":{"offsets":{"left":87,"top":-6},"sprite":{"left":94,"top":499,"width":49,"height":39}},"bb_counter_64_d_0_0":{"offsets":{"left":122,"top":-22},"sprite":{"left":192,"top":499,"width":50,"height":41}},"bb_counter_64_e_0_0":{"offsets":{"left":104,"top":-36},"sprite":{"left":0,"top":119,"width":20,"height":19}},"bb_counter_64_f_0_0":{"offsets":{"left":82,"top":-29},"sprite":{"left":59,"top":0,"width":12,"height":15}},"bb_counter_64_g_0_0":{"offsets":{"left":7,"top":126},"source":"bb_counter_64_i_0_0"},"bb_counter_64_g_0_1":{"offsets":{"left":7,"top":126},"sprite":{"left":28,"top":148,"width":35,"height":117}},"bb_counter_64_g_0_2":{"offsets":{"left":7,"top":126},"sprite":{"left":63,"top":148,"width":35,"height":117}},"bb_counter_64_g_0_3":{"offsets":{"left":7,"top":126},"sprite":{"left":98,"top":148,"width":35,"height":117}},"bb_counter_64_g_0_4":{"offsets":{"left":7,"top":126},"sprite":{"left":133,"top":148,"width":35,"height":117}},"bb_counter_64_g_0_5":{"offsets":{"left":7,"top":126},"sprite":{"left":168,"top":148,"width":35,"height":117}},"bb_counter_64_g_0_6":{"offsets":{"left":7,"top":126},"sprite":{"left":203,"top":148,"width":35,"height":117}},"bb_counter_64_g_0_7":{"offsets":{"left":7,"top":126},"sprite":{"left":0,"top":265,"width":35,"height":117}},"bb_counter_64_g_0_8":{"offsets":{"left":7,"top":126},"sprite":{"left":35,"top":265,"width":35,"height":117}},"bb_counter_64_g_0_9":{"offsets":{"left":7,"top":126},"sprite":{"left":70,"top":265,"width":35,"height":117}},"bb_counter_64_h_0_0":{"offsets":{"left":41,"top":109},"source":"bb_counter_64_i_0_0"},"bb_counter_64_i_0_0":{"offsets":{"left":83,"top":88},"sprite":{"left":175,"top":382,"width":35,"height":117}},"bb_counter_64_j_0_0":{"offsets":{"left":117,"top":71},"source":"bb_counter_64_i_0_0"},"bb_counter_64_k_0_0":{"offsets":{"left":49,"top":71},"sprite":{"left":21,"top":0,"width":9,"height":46}},"bb_counter_64_a_2_0":{"offsets":{"left":28,"top":30},"sprite":{"left":103,"top":540,"width":53,"height":43}},"bb_counter_64_b_2_0":{"offsets":{"left":-10,"top":10},"sprite":{"left":47,"top":499,"width":47,"height":38}},"bb_counter_64_c_2_0":{"offsets":{"left":-40,"top":-6},"sprite":{"left":143,"top":499,"width":49,"height":39}},"bb_counter_64_d_2_0":{"offsets":{"left":-74,"top":-22},"sprite":{"left":0,"top":540,"width":50,"height":41}},"bb_counter_64_e_2_0":{"offsets":{"left":22,"top":18},"sprite":{"left":20,"top":119,"width":20,"height":19}},"bb_counter_64_f_2_0":{"offsets":{"left":0,"top":7},"sprite":{"left":71,"top":0,"width":12,"height":15}},"bb_counter_64_g_2_0":{"offsets":{"left":-84,"top":71},"source":"bb_counter_64_i_2_0"},"bb_counter_64_g_2_1":{"offsets":{"left":-84,"top":71},"sprite":{"left":105,"top":265,"width":35,"height":117}},"bb_counter_64_g_2_2":{"offsets":{"left":-84,"top":71},"sprite":{"left":140,"top":265,"width":35,"height":117}},"bb_counter_64_g_2_3":{"offsets":{"left":-84,"top":71},"sprite":{"left":175,"top":265,"width":35,"height":117}},"bb_counter_64_g_2_4":{"offsets":{"left":-84,"top":71},"sprite":{"left":210,"top":265,"width":35,"height":117}},"bb_counter_64_g_2_5":{"offsets":{"left":-84,"top":71},"sprite":{"left":0,"top":382,"width":35,"height":117}},"bb_counter_64_g_2_6":{"offsets":{"left":-84,"top":71},"sprite":{"left":35,"top":382,"width":35,"height":117}},"bb_counter_64_g_2_7":{"offsets":{"left":-84,"top":71},"sprite":{"left":70,"top":382,"width":35,"height":117}},"bb_counter_64_g_2_8":{"offsets":{"left":-84,"top":71},"sprite":{"left":105,"top":382,"width":35,"height":117}},"bb_counter_64_g_2_9":{"offsets":{"left":-84,"top":71},"sprite":{"left":140,"top":382,"width":35,"height":117}},"bb_counter_64_h_2_0":{"offsets":{"left":-50,"top":88},"source":"bb_counter_64_i_2_0"},"bb_counter_64_i_2_0":{"offsets":{"left":-8,"top":109},"sprite":{"left":210,"top":382,"width":35,"height":117}},"bb_counter_64_j_2_0":{"offsets":{"left":26,"top":126},"source":"bb_counter_64_i_2_0"},"bb_counter_64_k_2_0":{"offsets":{"left":-42,"top":71},"sprite":{"left":30,"top":0,"width":9,"height":46}},"bb_counter_32_a_0_0":{"offsets":{"left":12,"top":18},"sprite":{"left":0,"top":148,"width":28,"height":23}},"bb_counter_32_b_0_0":{"offsets":{"left":28,"top":7},"sprite":{"left":64,"top":119,"width":25,"height":19}},"bb_counter_32_c_0_0":{"offsets":{"left":44,"top":-1},"sprite":{"left":114,"top":119,"width":26,"height":20}},"bb_counter_32_d_0_0":{"offsets":{"left":61,"top":-9},"sprite":{"left":166,"top":119,"width":26,"height":21}},"bb_counter_32_e_0_0":{"offsets":{"left":51,"top":-16},"sprite":{"left":39,"top":0,"width":10,"height":10}},"bb_counter_32_f_0_0":{"offsets":{"left":40,"top":-13},"sprite":{"left":9,"top":0,"width":6,"height":7}},"bb_counter_32_g_0_0":{"offsets":{"left":3,"top":66},"sprite":{"left":117,"top":0,"width":18,"height":59}},"bb_counter_32_g_0_1":{"offsets":{"left":3,"top":66},"sprite":{"left":135,"top":0,"width":18,"height":59}},"bb_counter_32_g_0_2":{"offsets":{"left":3,"top":66},"sprite":{"left":153,"top":0,"width":18,"height":59}},"bb_counter_32_g_0_3":{"offsets":{"left":3,"top":66},"sprite":{"left":171,"top":0,"width":18,"height":59}},"bb_counter_32_g_0_4":{"offsets":{"left":3,"top":66},"sprite":{"left":189,"top":0,"width":18,"height":59}},"bb_counter_32_g_0_5":{"offsets":{"left":3,"top":66},"sprite":{"left":207,"top":0,"width":18,"height":59}},"bb_counter_32_g_0_6":{"offsets":{"left":3,"top":66},"sprite":{"left":225,"top":0,"width":18,"height":59}},"bb_counter_32_g_0_7":{"offsets":{"left":3,"top":66},"sprite":{"left":0,"top":59,"width":18,"height":59}},"bb_counter_32_g_0_8":{"offsets":{"left":3,"top":66},"sprite":{"left":18,"top":59,"width":18,"height":59}},"bb_counter_32_g_0_9":{"offsets":{"left":3,"top":66},"sprite":{"left":36,"top":59,"width":18,"height":59}},"bb_counter_32_h_0_0":{"offsets":{"left":20,"top":57},"source":"bb_counter_32_j_0_0"},"bb_counter_32_i_0_0":{"offsets":{"left":41,"top":47},"source":"bb_counter_32_g_0_0"},"bb_counter_32_j_0_0":{"offsets":{"left":58,"top":38},"sprite":{"left":216,"top":59,"width":18,"height":58}},"bb_counter_32_k_0_0":{"offsets":{"left":24,"top":37},"sprite":{"left":4,"top":0,"width":5,"height":23}},"bb_counter_32_a_2_0":{"offsets":{"left":14,"top":18},"sprite":{"left":218,"top":119,"width":27,"height":22}},"bb_counter_32_b_2_0":{"offsets":{"left":-5,"top":8},"sprite":{"left":40,"top":119,"width":24,"height":20}},"bb_counter_32_c_2_0":{"offsets":{"left":-20,"top":0},"sprite":{"left":140,"top":119,"width":26,"height":20}},"bb_counter_32_d_2_0":{"offsets":{"left":-37,"top":-9},"sprite":{"left":192,"top":119,"width":26,"height":21}},"bb_counter_32_e_2_0":{"offsets":{"left":10,"top":11},"sprite":{"left":49,"top":0,"width":10,"height":10}},"bb_counter_32_f_2_0":{"offsets":{"left":-1,"top":5},"sprite":{"left":15,"top":0,"width":6,"height":7}},"bb_counter_32_g_2_0":{"offsets":{"left":-43,"top":38},"sprite":{"left":83,"top":0,"width":17,"height":58}},"bb_counter_32_g_2_1":{"offsets":{"left":-43,"top":38},"sprite":{"left":54,"top":59,"width":18,"height":60}},"bb_counter_32_g_2_2":{"offsets":{"left":-43,"top":38},"sprite":{"left":72,"top":59,"width":18,"height":60}},"bb_counter_32_g_2_3":{"offsets":{"left":-43,"top":38},"sprite":{"left":90,"top":59,"width":18,"height":60}},"bb_counter_32_g_2_4":{"offsets":{"left":-43,"top":38},"sprite":{"left":108,"top":59,"width":18,"height":60}},"bb_counter_32_g_2_5":{"offsets":{"left":-43,"top":38},"sprite":{"left":126,"top":59,"width":18,"height":60}},"bb_counter_32_g_2_6":{"offsets":{"left":-43,"top":38},"sprite":{"left":144,"top":59,"width":18,"height":60}},"bb_counter_32_g_2_7":{"offsets":{"left":-43,"top":38},"sprite":{"left":162,"top":59,"width":18,"height":60}},"bb_counter_32_g_2_8":{"offsets":{"left":-43,"top":38},"sprite":{"left":180,"top":59,"width":18,"height":60}},"bb_counter_32_g_2_9":{"offsets":{"left":-43,"top":38},"sprite":{"left":198,"top":59,"width":18,"height":60}},"bb_counter_32_h_2_0":{"offsets":{"left":-26,"top":47},"sprite":{"left":100,"top":0,"width":17,"height":59}},"bb_counter_32_i_2_0":{"offsets":{"left":-5,"top":57},"source":"bb_counter_32_g_2_0"},"bb_counter_32_j_2_0":{"offsets":{"left":12,"top":66},"source":"bb_counter_32_h_2_0"},"bb_counter_32_k_2_0":{"offsets":{"left":-22,"top":37},"sprite":{"left":0,"top":0,"width":4,"height":23}},"bb_counter_icon_a":{"offsets":{"left":12,"top":20},"sprite":{"left":89,"top":119,"width":25,"height":29}},"bb_counter_64_h_0_1":{"offsets":{"left":41,"top":109},"source":"bb_counter_64_g_0_1"},"bb_counter_64_h_0_2":{"offsets":{"left":41,"top":109},"source":"bb_counter_64_g_0_2"},"bb_counter_64_h_0_3":{"offsets":{"left":41,"top":109},"source":"bb_counter_64_g_0_3"},"bb_counter_64_h_0_4":{"offsets":{"left":41,"top":109},"source":"bb_counter_64_g_0_4"},"bb_counter_64_h_0_5":{"offsets":{"left":41,"top":109},"source":"bb_counter_64_g_0_5"},"bb_counter_64_h_0_6":{"offsets":{"left":41,"top":109},"source":"bb_counter_64_g_0_6"},"bb_counter_64_h_0_7":{"offsets":{"left":41,"top":109},"source":"bb_counter_64_g_0_7"},"bb_counter_64_h_0_8":{"offsets":{"left":41,"top":109},"source":"bb_counter_64_g_0_8"},"bb_counter_64_h_0_9":{"offsets":{"left":41,"top":109},"source":"bb_counter_64_g_0_9"},"bb_counter_64_h_2_1":{"offsets":{"left":-50,"top":88},"source":"bb_counter_64_g_2_1"},"bb_counter_64_h_2_2":{"offsets":{"left":-50,"top":88},"source":"bb_counter_64_g_2_2"},"bb_counter_64_h_2_3":{"offsets":{"left":-50,"top":88},"source":"bb_counter_64_g_2_3"},"bb_counter_64_h_2_4":{"offsets":{"left":-50,"top":88},"source":"bb_counter_64_g_2_4"},"bb_counter_64_h_2_5":{"offsets":{"left":-50,"top":88},"source":"bb_counter_64_g_2_5"},"bb_counter_64_h_2_6":{"offsets":{"left":-50,"top":88},"source":"bb_counter_64_g_2_6"},"bb_counter_64_h_2_7":{"offsets":{"left":-50,"top":88},"source":"bb_counter_64_g_2_7"},"bb_counter_64_h_2_8":{"offsets":{"left":-50,"top":88},"source":"bb_counter_64_g_2_8"},"bb_counter_64_h_2_9":{"offsets":{"left":-50,"top":88},"source":"bb_counter_64_g_2_9"},"bb_counter_64_i_0_1":{"offsets":{"left":83,"top":88},"source":"bb_counter_64_g_0_1"},"bb_counter_64_i_0_2":{"offsets":{"left":83,"top":88},"source":"bb_counter_64_g_0_2"},"bb_counter_64_i_0_3":{"offsets":{"left":83,"top":88},"source":"bb_counter_64_g_0_3"},"bb_counter_64_i_0_4":{"offsets":{"left":83,"top":88},"source":"bb_counter_64_g_0_4"},"bb_counter_64_i_0_5":{"offsets":{"left":83,"top":88},"source":"bb_counter_64_g_0_5"},"bb_counter_64_i_0_6":{"offsets":{"left":83,"top":88},"source":"bb_counter_64_g_0_6"},"bb_counter_64_i_0_7":{"offsets":{"left":83,"top":88},"source":"bb_counter_64_g_0_7"},"bb_counter_64_i_0_8":{"offsets":{"left":83,"top":88},"source":"bb_counter_64_g_0_8"},"bb_counter_64_i_0_9":{"offsets":{"left":83,"top":88},"source":"bb_counter_64_g_0_9"},"bb_counter_64_i_2_1":{"offsets":{"left":-8,"top":109},"source":"bb_counter_64_g_2_1"},"bb_counter_64_i_2_2":{"offsets":{"left":-8,"top":109},"source":"bb_counter_64_g_2_2"},"bb_counter_64_i_2_3":{"offsets":{"left":-8,"top":109},"source":"bb_counter_64_g_2_3"},"bb_counter_64_i_2_4":{"offsets":{"left":-8,"top":109},"source":"bb_counter_64_g_2_4"},"bb_counter_64_i_2_5":{"offsets":{"left":-8,"top":109},"source":"bb_counter_64_g_2_5"},"bb_counter_64_i_2_6":{"offsets":{"left":-8,"top":109},"source":"bb_counter_64_g_2_6"},"bb_counter_64_i_2_7":{"offsets":{"left":-8,"top":109},"source":"bb_counter_64_g_2_7"},"bb_counter_64_i_2_8":{"offsets":{"left":-8,"top":109},"source":"bb_counter_64_g_2_8"},"bb_counter_64_i_2_9":{"offsets":{"left":-8,"top":109},"source":"bb_counter_64_g_2_9"},"bb_counter_64_j_0_1":{"offsets":{"left":117,"top":71},"source":"bb_counter_64_g_0_1"},"bb_counter_64_j_0_2":{"offsets":{"left":117,"top":71},"source":"bb_counter_64_g_0_2"},"bb_counter_64_j_0_3":{"offsets":{"left":117,"top":71},"source":"bb_counter_64_g_0_3"},"bb_counter_64_j_0_4":{"offsets":{"left":117,"top":71},"source":"bb_counter_64_g_0_4"},"bb_counter_64_j_0_5":{"offsets":{"left":117,"top":71},"source":"bb_counter_64_g_0_5"},"bb_counter_64_j_0_6":{"offsets":{"left":117,"top":71},"source":"bb_counter_64_g_0_6"},"bb_counter_64_j_0_7":{"offsets":{"left":117,"top":71},"source":"bb_counter_64_g_0_7"},"bb_counter_64_j_0_8":{"offsets":{"left":117,"top":71},"source":"bb_counter_64_g_0_8"},"bb_counter_64_j_0_9":{"offsets":{"left":117,"top":71},"source":"bb_counter_64_g_0_9"},"bb_counter_64_j_2_1":{"offsets":{"left":26,"top":126},"source":"bb_counter_64_g_2_1"},"bb_counter_64_j_2_2":{"offsets":{"left":26,"top":126},"source":"bb_counter_64_g_2_2"},"bb_counter_64_j_2_3":{"offsets":{"left":26,"top":126},"source":"bb_counter_64_g_2_3"},"bb_counter_64_j_2_4":{"offsets":{"left":26,"top":126},"source":"bb_counter_64_g_2_4"},"bb_counter_64_j_2_5":{"offsets":{"left":26,"top":126},"source":"bb_counter_64_g_2_5"},"bb_counter_64_j_2_6":{"offsets":{"left":26,"top":126},"source":"bb_counter_64_g_2_6"},"bb_counter_64_j_2_7":{"offsets":{"left":26,"top":126},"source":"bb_counter_64_g_2_7"},"bb_counter_64_j_2_8":{"offsets":{"left":26,"top":126},"source":"bb_counter_64_g_2_8"},"bb_counter_64_j_2_9":{"offsets":{"left":26,"top":126},"source":"bb_counter_64_g_2_9"},"bb_counter_32_h_0_1":{"offsets":{"left":20,"top":57},"source":"bb_counter_32_g_0_1"},"bb_counter_32_h_0_2":{"offsets":{"left":20,"top":57},"source":"bb_counter_32_g_0_2"},"bb_counter_32_h_0_3":{"offsets":{"left":20,"top":57},"source":"bb_counter_32_g_0_3"},"bb_counter_32_h_0_4":{"offsets":{"left":20,"top":57},"source":"bb_counter_32_g_0_4"},"bb_counter_32_h_0_5":{"offsets":{"left":20,"top":57},"source":"bb_counter_32_g_0_5"},"bb_counter_32_h_0_6":{"offsets":{"left":20,"top":57},"source":"bb_counter_32_g_0_6"},"bb_counter_32_h_0_7":{"offsets":{"left":20,"top":57},"source":"bb_counter_32_g_0_7"},"bb_counter_32_h_0_8":{"offsets":{"left":20,"top":57},"source":"bb_counter_32_g_0_8"},"bb_counter_32_h_0_9":{"offsets":{"left":20,"top":57},"source":"bb_counter_32_g_0_9"},"bb_counter_32_h_2_1":{"offsets":{"left":-26,"top":47},"source":"bb_counter_32_g_2_1"},"bb_counter_32_h_2_2":{"offsets":{"left":-26,"top":47},"source":"bb_counter_32_g_2_2"},"bb_counter_32_h_2_3":{"offsets":{"left":-26,"top":47},"source":"bb_counter_32_g_2_3"},"bb_counter_32_h_2_4":{"offsets":{"left":-26,"top":47},"source":"bb_counter_32_g_2_4"},"bb_counter_32_h_2_5":{"offsets":{"left":-26,"top":47},"source":"bb_counter_32_g_2_5"},"bb_counter_32_h_2_6":{"offsets":{"left":-26,"top":47},"source":"bb_counter_32_g_2_6"},"bb_counter_32_h_2_7":{"offsets":{"left":-26,"top":47},"source":"bb_counter_32_g_2_7"},"bb_counter_32_h_2_8":{"offsets":{"left":-26,"top":47},"source":"bb_counter_32_g_2_8"},"bb_counter_32_h_2_9":{"offsets":{"left":-26,"top":47},"source":"bb_counter_32_g_2_9"},"bb_counter_32_i_0_1":{"offsets":{"left":41,"top":47},"source":"bb_counter_32_g_0_1"},"bb_counter_32_i_0_2":{"offsets":{"left":41,"top":47},"source":"bb_counter_32_g_0_2"},"bb_counter_32_i_0_3":{"offsets":{"left":41,"top":47},"source":"bb_counter_32_g_0_3"},"bb_counter_32_i_0_4":{"offsets":{"left":41,"top":47},"source":"bb_counter_32_g_0_4"},"bb_counter_32_i_0_5":{"offsets":{"left":41,"top":47},"source":"bb_counter_32_g_0_5"},"bb_counter_32_i_0_6":{"offsets":{"left":41,"top":47},"source":"bb_counter_32_g_0_6"},"bb_counter_32_i_0_7":{"offsets":{"left":41,"top":47},"source":"bb_counter_32_g_0_7"},"bb_counter_32_i_0_8":{"offsets":{"left":41,"top":47},"source":"bb_counter_32_g_0_8"},"bb_counter_32_i_0_9":{"offsets":{"left":41,"top":47},"source":"bb_counter_32_g_0_9"},"bb_counter_32_i_2_1":{"offsets":{"left":-5,"top":57},"source":"bb_counter_32_g_2_1"},"bb_counter_32_i_2_2":{"offsets":{"left":-5,"top":57},"source":"bb_counter_32_g_2_2"},"bb_counter_32_i_2_3":{"offsets":{"left":-5,"top":57},"source":"bb_counter_32_g_2_3"},"bb_counter_32_i_2_4":{"offsets":{"left":-5,"top":57},"source":"bb_counter_32_g_2_4"},"bb_counter_32_i_2_5":{"offsets":{"left":-5,"top":57},"source":"bb_counter_32_g_2_5"},"bb_counter_32_i_2_6":{"offsets":{"left":-5,"top":57},"source":"bb_counter_32_g_2_6"},"bb_counter_32_i_2_7":{"offsets":{"left":-5,"top":57},"source":"bb_counter_32_g_2_7"},"bb_counter_32_i_2_8":{"offsets":{"left":-5,"top":57},"source":"bb_counter_32_g_2_8"},"bb_counter_32_i_2_9":{"offsets":{"left":-5,"top":57},"source":"bb_counter_32_g_2_9"},"bb_counter_32_j_0_1":{"offsets":{"left":58,"top":38},"source":"bb_counter_32_g_0_1"},"bb_counter_32_j_0_2":{"offsets":{"left":58,"top":38},"source":"bb_counter_32_g_0_2"},"bb_counter_32_j_0_3":{"offsets":{"left":58,"top":38},"source":"bb_counter_32_g_0_3"},"bb_counter_32_j_0_4":{"offsets":{"left":58,"top":38},"source":"bb_counter_32_g_0_4"},"bb_counter_32_j_0_5":{"offsets":{"left":58,"top":38},"source":"bb_counter_32_g_0_5"},"bb_counter_32_j_0_6":{"offsets":{"left":58,"top":38},"source":"bb_counter_32_g_0_6"},"bb_counter_32_j_0_7":{"offsets":{"left":58,"top":38},"source":"bb_counter_32_g_0_7"},"bb_counter_32_j_0_8":{"offsets":{"left":58,"top":38},"source":"bb_counter_32_g_0_8"},"bb_counter_32_j_0_9":{"offsets":{"left":58,"top":38},"source":"bb_counter_32_g_0_9"},"bb_counter_32_j_2_1":{"offsets":{"left":12,"top":66},"source":"bb_counter_32_g_2_1"},"bb_counter_32_j_2_2":{"offsets":{"left":12,"top":66},"source":"bb_counter_32_g_2_2"},"bb_counter_32_j_2_3":{"offsets":{"left":12,"top":66},"source":"bb_counter_32_g_2_3"},"bb_counter_32_j_2_4":{"offsets":{"left":12,"top":66},"source":"bb_counter_32_g_2_4"},"bb_counter_32_j_2_5":{"offsets":{"left":12,"top":66},"source":"bb_counter_32_g_2_5"},"bb_counter_32_j_2_6":{"offsets":{"left":12,"top":66},"source":"bb_counter_32_g_2_6"},"bb_counter_32_j_2_7":{"offsets":{"left":12,"top":66},"source":"bb_counter_32_g_2_7"},"bb_counter_32_j_2_8":{"offsets":{"left":12,"top":66},"source":"bb_counter_32_g_2_8"},"bb_counter_32_j_2_9":{"offsets":{"left":12,"top":66},"source":"bb_counter_32_g_2_9"}},"visualization":{"type":"furniture_counter_clock","layerCount":11,"layers":{"0":{"ink":"COPY"},"1":{"z":"1000"},"2":{"z":"2000"},"3":{"z":"3000"},"4":{"ink":"ADD","z":"3001","tag":"start_stop"},"5":{"ink":"div ","z":"3001","tag":"reset"},"6":{"ink":"ADD","z":"1","tag":"seconds_sprite","ignoreMouse":"1"},"7":{"ink":"ADD","z":"1001","tag":"ten_seconds_sprite","ignoreMouse":"1"},"8":{"ink":"ADD","z":"2001","tag":"minutes_sprite","ignoreMouse":"1"},"9":{"ink":"ADD","z":"3001","tag":"ten_minutes_sprite","ignoreMouse":"1"},"10":{"z":"1500","ink":"ADD","ignoreMouse":"1"}},"directions":{"0":{},"2":{"4":{"z":"1"},"5":{"z":"1"},"6":{"z":"3001"},"7":{"z":"2001"},"8":{"z":"1001"},"9":{"z":"1"}}},"colors":{},"animations":{"0":{"layers":{"0":{"sequences":[[{"frame":0}]]},"1":{"sequences":[[{"frame":0}]]},"2":{"sequences":[[{"frame":0}]]},"3":{"sequences":[[{"frame":0}]]},"4":{"sequences":[[{"frame":0}]]},"5":{"sequences":[[{"frame":0}]]},"6":{"sequences":[[{"frame":0}]]},"7":{"sequences":[[{"frame":0}]]},"8":{"sequences":[[{"frame":0}]]},"9":{"sequences":[[{"frame":0}]]},"10":{"sequences":[[{"frame":0}]]}}}}},"logic":{"type":"furniture_counter_clock","dimensions":[1.0,4.0,1.0],"directions":[0,90],"particlesystems":[]}}