{"assets":{"penguin_ski_64_a_2_0":{"offsets":{"left":21,"top":55},"source":"penguin_ski_64_a_4_0","flipH":1},"penguin_ski_64_a_2_1":{"offsets":{"left":21,"top":55},"source":"penguin_ski_64_a_4_1","flipH":1},"penguin_ski_64_a_2_2":{"offsets":{"left":21,"top":55},"source":"penguin_ski_64_a_4_2","flipH":1},"penguin_ski_64_a_2_3":{"offsets":{"left":21,"top":55},"source":"penguin_ski_64_a_4_3","flipH":1},"penguin_ski_64_a_2_4":{"offsets":{"left":21,"top":55},"source":"penguin_ski_64_a_4_4","flipH":1},"penguin_ski_64_a_2_5":{"offsets":{"left":21,"top":55},"source":"penguin_ski_64_a_4_5","flipH":1},"penguin_ski_64_a_2_6":{"offsets":{"left":23,"top":55},"source":"penguin_ski_64_a_4_6","flipH":1},"penguin_ski_64_a_2_7":{"offsets":{"left":21,"top":55},"source":"penguin_ski_64_a_4_7","flipH":1},"penguin_ski_64_a_4_0":{"offsets":{"left":21,"top":55},"sprite":{"left":0,"top":169,"width":50,"height":65}},"penguin_ski_64_a_4_1":{"offsets":{"left":21,"top":55},"sprite":{"left":50,"top":169,"width":50,"height":65}},"penguin_ski_64_a_4_2":{"offsets":{"left":21,"top":55},"sprite":{"left":0,"top":234,"width":50,"height":65}},"penguin_ski_64_a_4_3":{"offsets":{"left":21,"top":55},"sprite":{"left":50,"top":234,"width":50,"height":65}},"penguin_ski_64_a_4_4":{"offsets":{"left":21,"top":55},"sprite":{"left":0,"top":299,"width":50,"height":65}},"penguin_ski_64_a_4_5":{"offsets":{"left":21,"top":55},"sprite":{"left":0,"top":105,"width":50,"height":63}},"penguin_ski_64_a_4_6":{"offsets":{"left":23,"top":55},"sprite":{"left":50,"top":105,"width":50,"height":64}},"penguin_ski_64_a_4_7":{"offsets":{"left":21,"top":55},"sprite":{"left":50,"top":299,"width":52,"height":66}},"penguin_ski_64_sd_2_0":{"offsets":{"left":21,"top":5},"source":"penguin_ski_64_sd_4_0","flipH":1},"penguin_ski_64_sd_4_0":{"offsets":{"left":21,"top":5},"sprite":{"left":21,"top":0,"width":37,"height":16}},"penguin_ski_icon_a":{"offsets":{"left":12,"top":15},"sprite":{"left":58,"top":0,"width":24,"height":30}},"penguin_ski_32_a_2_0":{"offsets":{"left":10,"top":28},"source":"penguin_ski_32_a_4_0","flipH":1},"penguin_ski_32_a_2_1":{"offsets":{"left":10,"top":28},"source":"penguin_ski_32_a_4_1","flipH":1},"penguin_ski_32_a_2_2":{"offsets":{"left":10,"top":28},"source":"penguin_ski_32_a_4_2","flipH":1},"penguin_ski_32_a_2_3":{"offsets":{"left":10,"top":28},"source":"penguin_ski_32_a_4_3","flipH":1},"penguin_ski_32_a_2_4":{"offsets":{"left":10,"top":28},"source":"penguin_ski_32_a_4_4","flipH":1},"penguin_ski_32_a_2_5":{"offsets":{"left":10,"top":28},"source":"penguin_ski_32_a_4_5","flipH":1},"penguin_ski_32_a_2_6":{"offsets":{"left":12,"top":28},"source":"penguin_ski_32_a_4_6","flipH":1},"penguin_ski_32_a_2_7":{"offsets":{"left":12,"top":28},"source":"penguin_ski_32_a_4_7","flipH":1},"penguin_ski_32_a_4_0":{"offsets":{"left":10,"top":28},"sprite":{"left":26,"top":34,"width":26,"height":35}},"penguin_ski_32_a_4_1":{"offsets":{"left":10,"top":28},"sprite":{"left":52,"top":34,"width":26,"height":35}},"penguin_ski_32_a_4_2":{"offsets":{"left":10,"top":28},"sprite":{"left":78,"top":34,"width":26,"height":35}},"penguin_ski_32_a_4_3":{"offsets":{"left":10,"top":28},"sprite":{"left":0,"top":69,"width":26,"height":35}},"penguin_ski_32_a_4_4":{"offsets":{"left":10,"top":28},"sprite":{"left":26,"top":69,"width":26,"height":35}},"penguin_ski_32_a_4_5":{"offsets":{"left":10,"top":28},"sprite":{"left":82,"top":0,"width":26,"height":34}},"penguin_ski_32_a_4_6":{"offsets":{"left":12,"top":28},"sprite":{"left":0,"top":34,"width":26,"height":34}},"penguin_ski_32_a_4_7":{"offsets":{"left":12,"top":28},"sprite":{"left":52,"top":69,"width":30,"height":36}},"penguin_ski_32_sd_2_0":{"offsets":{"left":11,"top":1},"source":"penguin_ski_32_sd_4_0","flipH":1},"penguin_ski_32_sd_4_0":{"offsets":{"left":11,"top":1},"sprite":{"left":0,"top":0,"width":21,"height":9}}},"visualization":{"type":"furniture_animated","layerCount":1,"layers":{},"directions":{"2":{},"4":{}},"colors":{},"animations":{"0":{"layers":{"0":{"sequences":[[{"frame":0},{"frame":0},{"frame":0},{"frame":0},{"frame":0},{"frame":0},{"frame":0},{"frame":0},{"frame":0},{"frame":0},{"frame":0},{"frame":0},{"frame":0},{"frame":0},{"frame":0},{"frame":0},{"frame":0},{"frame":0},{"frame":0},{"frame":0},{"frame":0},{"frame":0},{"frame":0},{"frame":0},{"frame":0},{"frame":0},{"frame":0},{"frame":0},{"frame":0},{"frame":0},{"frame":0},{"frame":0},{"frame":0},{"frame":0},{"frame":0},{"frame":0},{"frame":0},{"frame":0},{"frame":0},{"frame":0},{"frame":0},{"frame":0},{"frame":0},{"frame":0},{"frame":0},{"frame":0},{"frame":0},{"frame":0},{"frame":0},{"frame":1}],[{"frame":0},{"frame":0},{"frame":0},{"frame":0},{"frame":0},{"frame":0},{"frame":0},{"frame":0},{"frame":0},{"frame":0},{"frame":0},{"frame":0},{"frame":0},{"frame":0},{"frame":0},{"frame":0},{"frame":0},{"frame":0},{"frame":0},{"frame":0},{"frame":0},{"frame":0},{"frame":0},{"frame":0},{"frame":0},{"frame":0},{"frame":0},{"frame":0},{"frame":0},{"frame":0},{"frame":0},{"frame":0},{"frame":0},{"frame":0},{"frame":0},{"frame":0},{"frame":0},{"frame":0},{"frame":0},{"frame":0},{"frame":0},{"frame":0},{"frame":0},{"frame":0},{"frame":0},{"frame":0},{"frame":0},{"frame":0},{"frame":0},{"frame":0},{"frame":0},{"frame":0},{"frame":1}],[{"frame":0},{"frame":0},{"frame":0},{"frame":0},{"frame":0},{"frame":0},{"frame":0},{"frame":0},{"frame":0},{"frame":0},{"frame":0},{"frame":0},{"frame":0},{"frame":0},{"frame":0},{"frame":0},{"frame":0},{"frame":0},{"frame":0},{"frame":0},{"frame":0},{"frame":0},{"frame":0},{"frame":0},{"frame":0},{"frame":0},{"frame":0},{"frame":0},{"frame":0},{"frame":0},{"frame":0},{"frame":0},{"frame":0},{"frame":0},{"frame":0},{"frame":0},{"frame":0},{"frame":0},{"frame":0},{"frame":0},{"frame":0},{"frame":0},{"frame":0},{"frame":0},{"frame":0},{"frame":0},{"frame":0},{"frame":0},{"frame":1}],[{"frame":0},{"frame":0},{"frame":0},{"frame":0},{"frame":0},{"frame":0},{"frame":0},{"frame":0},{"frame":0},{"frame":0},{"frame":0},{"frame":0},{"frame":0},{"frame":0},{"frame":0},{"frame":0},{"frame":0},{"frame":0},{"frame":0},{"frame":0},{"frame":0},{"frame":0},{"frame":0},{"frame":0},{"frame":0},{"frame":0},{"frame":0},{"frame":0},{"frame":0},{"frame":0},{"frame":0},{"frame":0},{"frame":0},{"frame":0},{"frame":0},{"frame":0},{"frame":0},{"frame":0},{"frame":0},{"frame":0},{"frame":0},{"frame":0},{"frame":0},{"frame":0},{"frame":0},{"frame":0},{"frame":0},{"frame":0},{"frame":0},{"frame":0},{"frame":0},{"frame":0},{"frame":0},{"frame":0},{"frame":0},{"frame":1}],[{"frame":0},{"frame":0},{"frame":0},{"frame":0},{"frame":0},{"frame":0},{"frame":0},{"frame":0},{"frame":0},{"frame":0},{"frame":0},{"frame":0},{"frame":0},{"frame":0},{"frame":0},{"frame":0},{"frame":0},{"frame":0},{"frame":0},{"frame":0},{"frame":0},{"frame":0},{"frame":0},{"frame":0},{"frame":0},{"frame":0},{"frame":0},{"frame":0},{"frame":0},{"frame":0},{"frame":0},{"frame":0},{"frame":0},{"frame":0},{"frame":0},{"frame":0},{"frame":0},{"frame":0},{"frame":0},{"frame":0},{"frame":0},{"frame":0},{"frame":0},{"frame":0},{"frame":0},{"frame":0},{"frame":0},{"frame":0},{"frame":0},{"frame":0},{"frame":0},{"frame":0},{"frame":0},{"frame":0},{"frame":0},{"frame":0},{"frame":0},{"frame":0},{"frame":1}],[{"frame":0},{"frame":0},{"frame":0},{"frame":0},{"frame":0},{"frame":0},{"frame":0},{"frame":0},{"frame":0},{"frame":0},{"frame":0},{"frame":0},{"frame":0},{"frame":0},{"frame":0},{"frame":0},{"frame":0},{"frame":0},{"frame":0},{"frame":0},{"frame":0},{"frame":0},{"frame":0},{"frame":0},{"frame":0},{"frame":0},{"frame":0},{"frame":0},{"frame":0},{"frame":0},{"frame":0},{"frame":0},{"frame":0},{"frame":0},{"frame":0},{"frame":0},{"frame":0},{"frame":0},{"frame":0},{"frame":0},{"frame":0},{"frame":0},{"frame":0},{"frame":0},{"frame":0},{"frame":0},{"frame":0},{"frame":0},{"frame":0},{"frame":1}],[{"frame":0},{"frame":0},{"frame":0},{"frame":0},{"frame":0},{"frame":0},{"frame":0},{"frame":0},{"frame":0},{"frame":0},{"frame":0},{"frame":0},{"frame":0},{"frame":0},{"frame":0},{"frame":0},{"frame":0},{"frame":0},{"frame":0},{"frame":0},{"frame":0},{"frame":0},{"frame":0},{"frame":0},{"frame":0},{"frame":0},{"frame":0},{"frame":0},{"frame":0},{"frame":0},{"frame":0},{"frame":0},{"frame":0},{"frame":0},{"frame":0},{"frame":0},{"frame":0},{"frame":0},{"frame":0},{"frame":0},{"frame":0},{"frame":0},{"frame":0},{"frame":0},{"frame":0},{"frame":0},{"frame":0},{"frame":0},{"frame":0},{"frame":0},{"frame":0},{"frame":0},{"frame":0},{"frame":0},{"frame":1}],[{"frame":0},{"frame":0},{"frame":0},{"frame":0},{"frame":0},{"frame":0},{"frame":0},{"frame":0},{"frame":0},{"frame":0},{"frame":0},{"frame":0},{"frame":0},{"frame":0},{"frame":0},{"frame":0},{"frame":0},{"frame":0},{"frame":0},{"frame":0},{"frame":0},{"frame":0},{"frame":0},{"frame":0},{"frame":0},{"frame":0},{"frame":0},{"frame":0},{"frame":0},{"frame":0},{"frame":0},{"frame":0},{"frame":0},{"frame":0},{"frame":0},{"frame":0},{"frame":0},{"frame":0},{"frame":0},{"frame":0},{"frame":0},{"frame":0},{"frame":0},{"frame":0},{"frame":0},{"frame":0},{"frame":0},{"frame":0},{"frame":0},{"frame":0},{"frame":0},{"frame":0},{"frame":0},{"frame":0},{"frame":0},{"frame":0},{"frame":0},{"frame":0},{"frame":0},{"frame":0},{"frame":1}],[{"frame":0},{"frame":0},{"frame":0},{"frame":0},{"frame":0},{"frame":0},{"frame":0},{"frame":0},{"frame":0},{"frame":0},{"frame":0},{"frame":0},{"frame":0},{"frame":0},{"frame":0},{"frame":0},{"frame":0},{"frame":0},{"frame":0},{"frame":0},{"frame":0},{"frame":0},{"frame":0},{"frame":0},{"frame":0},{"frame":0},{"frame":0},{"frame":0},{"frame":0},{"frame":0},{"frame":0},{"frame":0},{"frame":0},{"frame":0},{"frame":0},{"frame":0},{"frame":0},{"frame":0},{"frame":0},{"frame":0},{"frame":0},{"frame":0},{"frame":0},{"frame":0},{"frame":0},{"frame":0},{"frame":0},{"frame":1}],[{"frame":0},{"frame":0},{"frame":0},{"frame":0},{"frame":0},{"frame":0},{"frame":0},{"frame":0},{"frame":0},{"frame":0},{"frame":0},{"frame":0},{"frame":0},{"frame":0},{"frame":0},{"frame":0},{"frame":0},{"frame":0},{"frame":0},{"frame":0},{"frame":0},{"frame":0},{"frame":0},{"frame":0},{"frame":0},{"frame":0},{"frame":0},{"frame":0},{"frame":0},{"frame":0},{"frame":6},{"frame":6},{"frame":0},{"frame":7},{"frame":7},{"frame":0},{"frame":6},{"frame":6},{"frame":0},{"frame":7},{"frame":7},{"frame":0},{"frame":6},{"frame":6},{"frame":0},{"frame":7},{"frame":7},{"frame":0},{"frame":6},{"frame":6},{"frame":0},{"frame":7},{"frame":7},{"frame":0},{"frame":0},{"frame":0},{"frame":0},{"frame":0},{"frame":0},{"frame":0},{"frame":1}],[{"frame":0},{"frame":0},{"frame":0},{"frame":0},{"frame":0},{"frame":0},{"frame":0},{"frame":0},{"frame":0},{"frame":0},{"frame":0},{"frame":0},{"frame":0},{"frame":0},{"frame":0},{"frame":0},{"frame":0},{"frame":0},{"frame":0},{"frame":0},{"frame":0},{"frame":0},{"frame":0},{"frame":0},{"frame":0},{"frame":0},{"frame":0},{"frame":0},{"frame":0},{"frame":0},{"frame":0},{"frame":0},{"frame":0},{"frame":4},{"frame":4},{"frame":0},{"frame":0},{"frame":5},{"frame":5},{"frame":0},{"frame":0},{"frame":4},{"frame":4},{"frame":0},{"frame":0},{"frame":5},{"frame":5},{"frame":0},{"frame":0},{"frame":4},{"frame":4},{"frame":0},{"frame":0},{"frame":5},{"frame":5},{"frame":0},{"frame":0},{"frame":0},{"frame":0},{"frame":0},{"frame":0},{"frame":1}],[{"frame":0},{"frame":0},{"frame":0},{"frame":0},{"frame":0},{"frame":0},{"frame":0},{"frame":0},{"frame":0},{"frame":0},{"frame":0},{"frame":0},{"frame":0},{"frame":0},{"frame":0},{"frame":0},{"frame":0},{"frame":0},{"frame":0},{"frame":0},{"frame":0},{"frame":0},{"frame":0},{"frame":0},{"frame":0},{"frame":0},{"frame":0},{"frame":0},{"frame":0},{"frame":0},{"frame":0},{"frame":0},{"frame":0},{"frame":0},{"frame":2},{"frame":2},{"frame":2},{"frame":2},{"frame":2},{"frame":2},{"frame":2},{"frame":2},{"frame":2},{"frame":2},{"frame":2},{"frame":2},{"frame":2},{"frame":2},{"frame":0},{"frame":0},{"frame":0},{"frame":0},{"frame":0},{"frame":0},{"frame":1}],[{"frame":0},{"frame":0},{"frame":0},{"frame":0},{"frame":0},{"frame":0},{"frame":0},{"frame":0},{"frame":0},{"frame":0},{"frame":0},{"frame":0},{"frame":0},{"frame":0},{"frame":0},{"frame":0},{"frame":0},{"frame":0},{"frame":0},{"frame":0},{"frame":0},{"frame":0},{"frame":0},{"frame":0},{"frame":0},{"frame":0},{"frame":0},{"frame":0},{"frame":3},{"frame":3},{"frame":3},{"frame":3},{"frame":0},{"frame":0},{"frame":0},{"frame":0},{"frame":3},{"frame":3},{"frame":0},{"frame":0},{"frame":3},{"frame":3},{"frame":0},{"frame":0},{"frame":1}],[{"frame":0},{"frame":0},{"frame":0},{"frame":0},{"frame":0},{"frame":0},{"frame":0},{"frame":0},{"frame":0},{"frame":0},{"frame":0},{"frame":0},{"frame":0},{"frame":0},{"frame":0},{"frame":0},{"frame":0},{"frame":0},{"frame":0},{"frame":0},{"frame":0},{"frame":0},{"frame":0},{"frame":0},{"frame":0},{"frame":0},{"frame":0},{"frame":0},{"frame":1},{"frame":1},{"frame":1},{"frame":0},{"frame":0},{"frame":0},{"frame":0},{"frame":0},{"frame":0},{"frame":1},{"frame":1},{"frame":1},{"frame":1},{"frame":1},{"frame":1},{"frame":0},{"frame":0},{"frame":0},{"frame":0},{"frame":0},{"frame":0},{"frame":0},{"frame":0},{"frame":0},{"frame":1},{"frame":1},{"frame":1},{"frame":1},{"frame":1},{"frame":1},{"frame":1},{"frame":1},{"frame":1},{"frame":1},{"frame":1},{"frame":1},{"frame":1},{"frame":1},{"frame":1},{"frame":1},{"frame":1},{"frame":1},{"frame":1},{"frame":1},{"frame":1},{"frame":1},{"frame":1},{"frame":1},{"frame":1},{"frame":1},{"frame":1},{"frame":1},{"frame":1},{"frame":1},{"frame":1},{"frame":1},{"frame":1},{"frame":1},{"frame":1},{"frame":1},{"frame":1},{"frame":1},{"frame":1},{"frame":1},{"frame":1},{"frame":1},{"frame":1},{"frame":1},{"frame":1},{"frame":0},{"frame":0},{"frame":0},{"frame":0},{"frame":0},{"frame":0},{"frame":1},{"frame":1},{"frame":1},{"frame":1},{"frame":1},{"frame":1},{"frame":0},{"frame":0},{"frame":0},{"frame":0},{"frame":0},{"frame":0},{"frame":1}],[{"frame":0},{"frame":0},{"frame":0},{"frame":0},{"frame":0},{"frame":0},{"frame":0},{"frame":0},{"frame":0},{"frame":0},{"frame":0},{"frame":0},{"frame":0},{"frame":0},{"frame":0},{"frame":0},{"frame":0},{"frame":0},{"frame":0},{"frame":0},{"frame":0},{"frame":0},{"frame":0},{"frame":0},{"frame":0},{"frame":0},{"frame":0},{"frame":0},{"frame":0},{"frame":0},{"frame":0},{"frame":0},{"frame":4},{"frame":5},{"frame":4},{"frame":5},{"frame":4},{"frame":5},{"frame":4},{"frame":5},{"frame":4},{"frame":5},{"frame":0},{"frame":0},{"frame":0},{"frame":0},{"frame":0},{"frame":0},{"frame":0},{"frame":1}]],"loopCount":0,"frameRepeat":4,"random":1}}}}},"logic":{"type":"furniture_multistate","dimensions":[1.0,1.0,0.0],"directions":[90,180],"particlesystems":[]}}