{"assets":{"party_ravel_64_a_2_0":{"offsets":{"left":28,"top":106},"source":"party_ravel_64_a_4_0","flipH":1},"party_ravel_64_a_4_0":{"offsets":{"left":28,"top":106},"sprite":{"left":0,"top":768,"width":56,"height":108}},"party_ravel_64_b_2_0":{"offsets":{"left":33,"top":1},"source":"party_ravel_64_b_4_0","flipH":1},"party_ravel_64_b_2_1":{"offsets":{"left":91,"top":122},"source":"party_ravel_64_b_4_4","flipH":1},"party_ravel_64_b_2_2":{"offsets":{"left":70,"top":90},"source":"party_ravel_64_b_4_3","flipH":1},"party_ravel_64_b_2_3":{"offsets":{"left":8,"top":144},"source":"party_ravel_64_b_4_2","flipH":1},"party_ravel_64_b_2_4":{"offsets":{"left":55,"top":168},"source":"party_ravel_64_b_4_1","flipH":1},"party_ravel_64_b_2_5":{"offsets":{"left":60,"top":89},"source":"party_ravel_64_b_4_5","flipH":1},"party_ravel_64_b_2_6":{"offsets":{"left":65,"top":89},"source":"party_ravel_64_b_4_6","flipH":1},"party_ravel_64_b_2_7":{"offsets":{"left":65,"top":90},"source":"party_ravel_64_b_4_7","flipH":1},"party_ravel_64_b_2_8":{"offsets":{"left":60,"top":125},"source":"party_ravel_64_b_4_8","flipH":1},"party_ravel_64_b_2_9":{"offsets":{"left":64,"top":158},"source":"party_ravel_64_b_4_9","flipH":1},"party_ravel_64_b_4_0":{"offsets":{"left":33,"top":1},"source":"party_ravel_32_b_4_0"},"party_ravel_64_b_4_1":{"offsets":{"left":55,"top":168},"sprite":{"left":0,"top":497,"width":54,"height":84}},"party_ravel_64_b_4_2":{"offsets":{"left":8,"top":144},"sprite":{"left":0,"top":581,"width":109,"height":89}},"party_ravel_64_b_4_3":{"offsets":{"left":70,"top":90},"sprite":{"left":0,"top":353,"width":126,"height":71}},"party_ravel_64_b_4_4":{"offsets":{"left":91,"top":122},"sprite":{"left":0,"top":902,"width":100,"height":135}},"party_ravel_64_b_4_5":{"offsets":{"left":60,"top":89},"sprite":{"left":56,"top":768,"width":64,"height":134}},"party_ravel_64_b_4_6":{"offsets":{"left":65,"top":89},"sprite":{"left":0,"top":670,"width":82,"height":98}},"party_ravel_64_b_4_7":{"offsets":{"left":65,"top":90},"sprite":{"left":0,"top":230,"width":92,"height":54}},"party_ravel_64_b_4_8":{"offsets":{"left":60,"top":125},"sprite":{"left":0,"top":179,"width":101,"height":51}},"party_ravel_64_b_4_9":{"offsets":{"left":64,"top":158},"sprite":{"left":0,"top":424,"width":109,"height":73}},"party_ravel_64_c_2_0":{"offsets":{"left":10,"top":14},"source":"party_ravel_64_c_4_0","flipH":1},"party_ravel_64_c_4_0":{"offsets":{"left":10,"top":14},"sprite":{"left":101,"top":25,"width":20,"height":28}},"party_ravel_64_sd_2_0":{"offsets":{"left":28,"top":11},"source":"party_ravel_64_sd_4_0","flipH":1},"party_ravel_64_sd_4_0":{"offsets":{"left":28,"top":11},"sprite":{"left":0,"top":25,"width":56,"height":26}},"party_ravel_icon_a":{"offsets":{"left":6,"top":15},"sprite":{"left":0,"top":53,"width":13,"height":30}},"party_ravel_32_a_2_0":{"offsets":{"left":15,"top":53},"source":"party_ravel_32_a_4_0","flipH":1},"party_ravel_32_a_4_0":{"offsets":{"left":15,"top":53},"sprite":{"left":92,"top":230,"width":29,"height":55}},"party_ravel_32_b_2_0":{"offsets":{"left":17,"top":1},"source":"party_ravel_32_b_4_0","flipH":1},"party_ravel_32_b_2_1":{"offsets":{"left":46,"top":62},"source":"party_ravel_32_b_4_4","flipH":1},"party_ravel_32_b_2_2":{"offsets":{"left":36,"top":46},"source":"party_ravel_32_b_4_3","flipH":1},"party_ravel_32_b_2_3":{"offsets":{"left":4,"top":72},"source":"party_ravel_32_b_4_2","flipH":1},"party_ravel_32_b_2_4":{"offsets":{"left":29,"top":84},"source":"party_ravel_32_b_4_1","flipH":1},"party_ravel_32_b_2_5":{"offsets":{"left":30,"top":45},"source":"party_ravel_32_b_4_5","flipH":1},"party_ravel_32_b_2_6":{"offsets":{"left":33,"top":45},"source":"party_ravel_32_b_4_6","flipH":1},"party_ravel_32_b_2_7":{"offsets":{"left":32,"top":45},"source":"party_ravel_32_b_4_7","flipH":1},"party_ravel_32_b_2_8":{"offsets":{"left":31,"top":63},"source":"party_ravel_32_b_4_8","flipH":1},"party_ravel_32_b_2_9":{"offsets":{"left":32,"top":79},"source":"party_ravel_32_b_4_9","flipH":1},"party_ravel_32_b_4_0":{"offsets":{"left":17,"top":1},"sprite":{"left":0,"top":0,"width":2,"height":2}},"party_ravel_32_b_4_1":{"offsets":{"left":29,"top":84},"sprite":{"left":53,"top":89,"width":27,"height":42}},"party_ravel_32_b_4_2":{"offsets":{"left":4,"top":72},"sprite":{"left":0,"top":131,"width":54,"height":44}},"party_ravel_32_b_4_3":{"offsets":{"left":36,"top":46},"sprite":{"left":13,"top":53,"width":63,"height":36}},"party_ravel_32_b_4_4":{"offsets":{"left":46,"top":62},"sprite":{"left":32,"top":285,"width":50,"height":68}},"party_ravel_32_b_4_5":{"offsets":{"left":30,"top":45},"sprite":{"left":0,"top":285,"width":32,"height":66}},"party_ravel_32_b_4_6":{"offsets":{"left":33,"top":45},"sprite":{"left":54,"top":131,"width":41,"height":48}},"party_ravel_32_b_4_7":{"offsets":{"left":32,"top":45},"sprite":{"left":56,"top":25,"width":45,"height":27}},"party_ravel_32_b_4_8":{"offsets":{"left":31,"top":63},"sprite":{"left":36,"top":0,"width":49,"height":25}},"party_ravel_32_b_4_9":{"offsets":{"left":32,"top":79},"sprite":{"left":0,"top":89,"width":53,"height":36}},"party_ravel_32_c_2_0":{"offsets":{"left":3,"top":8},"source":"party_ravel_32_c_4_0","flipH":1},"party_ravel_32_c_4_0":{"offsets":{"left":3,"top":8},"sprite":{"left":31,"top":0,"width":5,"height":16}},"party_ravel_32_sd_2_0":{"offsets":{"left":14,"top":5},"source":"party_ravel_32_sd_4_0","flipH":1},"party_ravel_32_sd_4_0":{"offsets":{"left":14,"top":5},"sprite":{"left":2,"top":0,"width":29,"height":14}}},"visualization":{"type":"furniture_animated","layerCount":3,"layers":{"1":{"ink":"ADD","ignoreMouse":"1"}},"directions":{"2":{"0":{},"1":{"z":"2000"},"2":{}},"4":{"0":{},"1":{"z":"2000"},"2":{}}},"colors":{},"animations":{"0":{"layers":{"0":{"sequences":[[{"frame":0}]]},"1":{"sequences":[[{"frame":0}]]},"2":{"sequences":[[{"frame":0}]]}}},"1":{"layers":{"0":{"sequences":[[{"frame":0}]]},"1":{"sequences":[[{"frame":1},{"frame":3},{"frame":2},{"frame":4},{"frame":3},{"frame":1},{"frame":3},{"frame":2},{"frame":4},{"frame":1},{"frame":2},{"frame":4},{"frame":1},{"frame":3},{"frame":4},{"frame":2},{"frame":1},{"frame":3},{"frame":2},{"frame":4},{"frame":3},{"frame":1},{"frame":3},{"frame":2},{"frame":4},{"frame":1},{"frame":2},{"frame":4},{"frame":1},{"frame":3},{"frame":4},{"frame":2},{"frame":1},{"frame":3},{"frame":2},{"frame":4},{"frame":3},{"frame":1},{"frame":3},{"frame":2},{"frame":4},{"frame":1},{"frame":2},{"frame":4},{"frame":1},{"frame":3},{"frame":4},{"frame":2},{"frame":1},{"frame":2},{"frame":3},{"frame":4},{"frame":1},{"frame":2},{"frame":3},{"frame":4},{"frame":1},{"frame":2},{"frame":3},{"frame":4},{"frame":1},{"frame":2},{"frame":3},{"frame":4},{"frame":1},{"frame":2},{"frame":3},{"frame":4},{"frame":1},{"frame":2},{"frame":3},{"frame":4}]],"loopCount":0,"frameRepeat":4},"2":{"sequences":[[{"frame":0}]]}}},"2":{"layers":{"0":{"sequences":[[{"frame":0}]]},"1":{"sequences":[[{"frame":5},{"frame":5},{"frame":5},{"frame":5},{"frame":6},{"frame":7},{"frame":8},{"frame":9},{"frame":9},{"frame":9},{"frame":9},{"frame":8},{"frame":7},{"frame":6},{"frame":5},{"frame":5},{"frame":5},{"frame":5},{"frame":6},{"frame":7},{"frame":8},{"frame":9},{"frame":9},{"frame":9},{"frame":9},{"frame":8},{"frame":7},{"frame":6},{"frame":5},{"frame":5},{"frame":5},{"frame":5},{"frame":6},{"frame":7},{"frame":8},{"frame":9},{"frame":9},{"frame":9},{"frame":9},{"frame":8},{"frame":7},{"frame":6},{"frame":5},{"frame":5},{"frame":5},{"frame":5},{"frame":6},{"frame":7},{"frame":8},{"frame":9},{"frame":9},{"frame":9},{"frame":9},{"frame":8},{"frame":7},{"frame":6},{"frame":5},{"frame":5},{"frame":5},{"frame":5},{"frame":6},{"frame":7},{"frame":8},{"frame":9},{"frame":9},{"frame":9},{"frame":9},{"frame":8},{"frame":7},{"frame":6},{"frame":5},{"frame":5},{"frame":9},{"frame":9},{"frame":9},{"frame":9},{"frame":8},{"frame":7},{"frame":6},{"frame":5},{"frame":5},{"frame":9},{"frame":9},{"frame":9},{"frame":9},{"frame":8},{"frame":7},{"frame":6},{"frame":5},{"frame":5},{"frame":9},{"frame":9},{"frame":9},{"frame":9},{"frame":8},{"frame":7},{"frame":6},{"frame":5},{"frame":5},{"frame":9},{"frame":9},{"frame":9},{"frame":9},{"frame":8},{"frame":7},{"frame":6},{"frame":5},{"frame":5}]],"loopCount":0,"frameRepeat":4},"2":{"sequences":[[{"frame":0}]]}}},"3":{"layers":{"0":{"sequences":[[{"frame":0}]]},"1":{"sequences":[[{"frame":1},{"frame":3},{"frame":2},{"frame":4},{"frame":3},{"frame":1},{"frame":3},{"frame":2},{"frame":4},{"frame":1},{"frame":2},{"frame":4},{"frame":1},{"frame":3},{"frame":4},{"frame":2},{"frame":1},{"frame":3},{"frame":2},{"frame":4},{"frame":3},{"frame":1},{"frame":3},{"frame":2},{"frame":4},{"frame":1},{"frame":2},{"frame":3},{"frame":4},{"frame":1},{"frame":3},{"frame":4},{"frame":2},{"frame":1},{"frame":5},{"frame":5},{"frame":5},{"frame":6},{"frame":7},{"frame":8},{"frame":9},{"frame":9},{"frame":9},{"frame":8},{"frame":7},{"frame":6},{"frame":5},{"frame":5},{"frame":5},{"frame":6},{"frame":7},{"frame":8},{"frame":9},{"frame":9},{"frame":9},{"frame":8},{"frame":7},{"frame":6},{"frame":5},{"frame":5},{"frame":5},{"frame":6},{"frame":7},{"frame":8},{"frame":9},{"frame":9},{"frame":9},{"frame":8},{"frame":7},{"frame":6},{"frame":5},{"frame":5},{"frame":5},{"frame":6},{"frame":7},{"frame":8},{"frame":9},{"frame":9},{"frame":9},{"frame":8},{"frame":7},{"frame":6},{"frame":5},{"frame":5},{"frame":5}]],"loopCount":0,"frameRepeat":4},"2":{"sequences":[[{"frame":0}]]}}}}},"logic":{"type":"furniture_multistate","dimensions":[1.0,1.0,0.0],"directions":[90,180],"particlesystems":[]}}