{"assets":{"ads_rangocactus_64_sd_0_0":{"offsets":{"left":18,"top":9},"sprite":{"left":0,"top":192,"width":36,"height":19}},"ads_rangocactus_64_a_0_0":{"offsets":{"left":44,"top":184},"sprite":{"left":56,"top":0,"width":72,"height":192}},"ads_rangocactus_32_sd_0_0":{"offsets":{"left":9,"top":4},"sprite":{"left":37,"top":0,"width":19,"height":10}},"ads_rangocactus_32_a_0_0":{"offsets":{"left":23,"top":92},"sprite":{"left":0,"top":0,"width":37,"height":97}},"ads_rangocactus_32_sd_2_0":{"offsets":{"left":9,"top":4},"source":"ads_rangocactus_32_sd_0_0","flipH":1},"ads_rangocactus_32_a_2_0":{"offsets":{"left":23,"top":92},"source":"ads_rangocactus_32_a_0_0","flipH":1},"ads_rangocactus_64_sd_2_0":{"offsets":{"left":18,"top":9},"source":"ads_rangocactus_64_sd_0_0","flipH":1},"ads_rangocactus_64_a_2_0":{"offsets":{"left":44,"top":184},"source":"ads_rangocactus_64_a_0_0","flipH":1},"ads_rangocactus_icon_a":{"offsets":{"left":8,"top":17},"sprite":{"left":36,"top":192,"width":20,"height":29}}},"visualization":{"type":"furniture_static","layerCount":1,"layers":{},"directions":{"0":{},"2":{}},"colors":{},"animations":{}},"logic":{"type":"furniture_basic","dimensions":[1.0,1.0,1.0],"directions":[0,90],"particlesystems":[]}}