{"assets":{"wf_cnd_not_match_snap_64_a_2_0":{"offsets":{"left":35,"top":33},"sprite":{"left":442,"top":0,"width":67,"height":49}},"wf_cnd_not_match_snap_64_a_2_1":{"offsets":{"left":35,"top":33},"sprite":{"left":509,"top":0,"width":67,"height":49}},"wf_cnd_not_match_snap_64_a_2_2":{"offsets":{"left":35,"top":33},"sprite":{"left":576,"top":0,"width":67,"height":49}},"wf_cnd_not_match_snap_64_a_2_3":{"offsets":{"left":35,"top":33},"sprite":{"left":643,"top":0,"width":67,"height":49}},"wf_cnd_not_match_snap_64_a_2_4":{"offsets":{"left":35,"top":33},"sprite":{"left":710,"top":0,"width":67,"height":49}},"wf_cnd_not_match_snap_64_a_2_5":{"offsets":{"left":35,"top":33},"sprite":{"left":777,"top":0,"width":67,"height":49}},"wf_cnd_not_match_snap_64_a_2_6":{"offsets":{"left":35,"top":33},"sprite":{"left":844,"top":0,"width":67,"height":49}},"wf_cnd_not_match_snap_64_a_2_7":{"offsets":{"left":35,"top":33},"sprite":{"left":911,"top":0,"width":67,"height":49}},"wf_cnd_not_match_snap_64_a_2_8":{"offsets":{"left":35,"top":33},"sprite":{"left":978,"top":0,"width":67,"height":49}},"wf_cnd_not_match_snap_64_a_2_9":{"offsets":{"left":35,"top":33},"sprite":{"left":1045,"top":0,"width":67,"height":49}},"wf_cnd_not_match_snap_64_a_2_10":{"offsets":{"left":35,"top":33},"sprite":{"left":1112,"top":0,"width":67,"height":49}},"wf_cnd_not_match_snap_64_a_2_11":{"offsets":{"left":35,"top":33},"sprite":{"left":1179,"top":0,"width":67,"height":49}},"wf_cnd_not_match_snap_64_a_2_12":{"offsets":{"left":35,"top":33},"sprite":{"left":1246,"top":0,"width":67,"height":49}},"wf_cnd_not_match_snap_64_a_2_13":{"offsets":{"left":35,"top":33},"sprite":{"left":1313,"top":0,"width":67,"height":49}},"wf_cnd_not_match_snap_64_a_2_14":{"offsets":{"left":35,"top":33},"source":"wf_cnd_not_match_snap_64_a_2_8"},"wf_cnd_not_match_snap_64_a_2_15":{"offsets":{"left":35,"top":33},"sprite":{"left":1380,"top":0,"width":67,"height":49}},"wf_cnd_not_match_snap_64_a_2_16":{"offsets":{"left":35,"top":33},"sprite":{"left":1447,"top":0,"width":67,"height":49}},"wf_cnd_not_match_snap_32_a_2_0":{"offsets":{"left":17,"top":16},"sprite":{"left":0,"top":0,"width":34,"height":25}},"wf_cnd_not_match_snap_32_a_2_1":{"offsets":{"left":17,"top":16},"sprite":{"left":34,"top":0,"width":34,"height":25}},"wf_cnd_not_match_snap_32_a_2_2":{"offsets":{"left":17,"top":16},"sprite":{"left":68,"top":0,"width":34,"height":25}},"wf_cnd_not_match_snap_32_a_2_3":{"offsets":{"left":17,"top":16},"sprite":{"left":102,"top":0,"width":34,"height":25}},"wf_cnd_not_match_snap_32_a_2_4":{"offsets":{"left":17,"top":16},"sprite":{"left":136,"top":0,"width":34,"height":25}},"wf_cnd_not_match_snap_32_a_2_5":{"offsets":{"left":17,"top":16},"sprite":{"left":170,"top":0,"width":34,"height":25}},"wf_cnd_not_match_snap_32_a_2_6":{"offsets":{"left":17,"top":16},"sprite":{"left":204,"top":0,"width":34,"height":25}},"wf_cnd_not_match_snap_32_a_2_7":{"offsets":{"left":17,"top":16},"source":"wf_cnd_not_match_snap_32_a_2_12"},"wf_cnd_not_match_snap_32_a_2_8":{"offsets":{"left":17,"top":16},"sprite":{"left":238,"top":0,"width":34,"height":25}},"wf_cnd_not_match_snap_32_a_2_9":{"offsets":{"left":17,"top":16},"sprite":{"left":272,"top":0,"width":34,"height":25}},"wf_cnd_not_match_snap_32_a_2_10":{"offsets":{"left":17,"top":16},"sprite":{"left":306,"top":0,"width":34,"height":25}},"wf_cnd_not_match_snap_32_a_2_11":{"offsets":{"left":17,"top":16},"sprite":{"left":340,"top":0,"width":34,"height":25}},"wf_cnd_not_match_snap_32_a_2_12":{"offsets":{"left":17,"top":16},"sprite":{"left":374,"top":0,"width":34,"height":25}},"wf_cnd_not_match_snap_32_a_2_13":{"offsets":{"left":17,"top":16},"sprite":{"left":408,"top":0,"width":34,"height":25}},"wf_cnd_not_match_snap_icon_a":{"offsets":{"left":15,"top":15},"sprite":{"left":1514,"top":0,"width":30,"height":30}},"wf_cnd_not_match_snap_64_a_6_0":{"offsets":{"left":35,"top":33},"source":"wf_cnd_not_match_snap_64_a_2_0","flipH":1},"wf_cnd_not_match_snap_64_a_6_1":{"offsets":{"left":35,"top":33},"source":"wf_cnd_not_match_snap_64_a_2_1","flipH":1},"wf_cnd_not_match_snap_64_a_6_2":{"offsets":{"left":35,"top":33},"source":"wf_cnd_not_match_snap_64_a_2_2","flipH":1},"wf_cnd_not_match_snap_64_a_6_3":{"offsets":{"left":35,"top":33},"source":"wf_cnd_not_match_snap_64_a_2_3","flipH":1},"wf_cnd_not_match_snap_64_a_6_4":{"offsets":{"left":35,"top":33},"source":"wf_cnd_not_match_snap_64_a_2_4","flipH":1},"wf_cnd_not_match_snap_64_a_6_5":{"offsets":{"left":35,"top":33},"source":"wf_cnd_not_match_snap_64_a_2_5","flipH":1},"wf_cnd_not_match_snap_64_a_6_6":{"offsets":{"left":35,"top":33},"source":"wf_cnd_not_match_snap_64_a_2_6","flipH":1},"wf_cnd_not_match_snap_64_a_6_7":{"offsets":{"left":35,"top":33},"source":"wf_cnd_not_match_snap_64_a_2_7","flipH":1},"wf_cnd_not_match_snap_64_a_6_8":{"offsets":{"left":35,"top":33},"source":"wf_cnd_not_match_snap_64_a_2_8","flipH":1},"wf_cnd_not_match_snap_64_a_6_9":{"offsets":{"left":35,"top":33},"source":"wf_cnd_not_match_snap_64_a_2_9","flipH":1},"wf_cnd_not_match_snap_64_a_6_10":{"offsets":{"left":35,"top":33},"source":"wf_cnd_not_match_snap_64_a_2_10","flipH":1},"wf_cnd_not_match_snap_64_a_6_11":{"offsets":{"left":35,"top":33},"source":"wf_cnd_not_match_snap_64_a_2_11","flipH":1},"wf_cnd_not_match_snap_64_a_6_12":{"offsets":{"left":35,"top":33},"source":"wf_cnd_not_match_snap_64_a_2_12","flipH":1},"wf_cnd_not_match_snap_64_a_6_13":{"offsets":{"left":35,"top":33},"source":"wf_cnd_not_match_snap_64_a_2_13","flipH":1},"wf_cnd_not_match_snap_64_a_6_14":{"offsets":{"left":35,"top":33},"source":"wf_cnd_not_match_snap_64_a_2_14","flipH":1},"wf_cnd_not_match_snap_64_a_6_15":{"offsets":{"left":35,"top":33},"source":"wf_cnd_not_match_snap_64_a_2_15","flipH":1},"wf_cnd_not_match_snap_64_a_6_16":{"offsets":{"left":35,"top":33},"source":"wf_cnd_not_match_snap_64_a_2_16","flipH":1},"wf_cnd_not_match_snap_32_a_6_0":{"offsets":{"left":17,"top":16},"source":"wf_cnd_not_match_snap_32_a_2_0","flipH":1},"wf_cnd_not_match_snap_32_a_6_1":{"offsets":{"left":17,"top":16},"source":"wf_cnd_not_match_snap_32_a_2_1","flipH":1},"wf_cnd_not_match_snap_32_a_6_2":{"offsets":{"left":17,"top":16},"source":"wf_cnd_not_match_snap_32_a_2_2","flipH":1},"wf_cnd_not_match_snap_32_a_6_3":{"offsets":{"left":17,"top":16},"source":"wf_cnd_not_match_snap_32_a_2_3","flipH":1},"wf_cnd_not_match_snap_32_a_6_4":{"offsets":{"left":17,"top":16},"source":"wf_cnd_not_match_snap_32_a_2_4","flipH":1},"wf_cnd_not_match_snap_32_a_6_5":{"offsets":{"left":17,"top":16},"source":"wf_cnd_not_match_snap_32_a_2_5","flipH":1},"wf_cnd_not_match_snap_32_a_6_6":{"offsets":{"left":17,"top":16},"source":"wf_cnd_not_match_snap_32_a_2_6","flipH":1},"wf_cnd_not_match_snap_32_a_6_7":{"offsets":{"left":17,"top":16},"source":"wf_cnd_not_match_snap_32_a_2_7","flipH":1},"wf_cnd_not_match_snap_32_a_6_8":{"offsets":{"left":17,"top":16},"source":"wf_cnd_not_match_snap_32_a_2_8","flipH":1},"wf_cnd_not_match_snap_32_a_6_9":{"offsets":{"left":17,"top":16},"source":"wf_cnd_not_match_snap_32_a_2_9","flipH":1},"wf_cnd_not_match_snap_32_a_6_10":{"offsets":{"left":17,"top":16},"source":"wf_cnd_not_match_snap_32_a_2_10","flipH":1},"wf_cnd_not_match_snap_32_a_6_11":{"offsets":{"left":17,"top":16},"source":"wf_cnd_not_match_snap_32_a_2_11","flipH":1},"wf_cnd_not_match_snap_32_a_6_12":{"offsets":{"left":17,"top":16},"source":"wf_cnd_not_match_snap_32_a_2_12","flipH":1},"wf_cnd_not_match_snap_32_a_6_13":{"offsets":{"left":17,"top":16},"source":"wf_cnd_not_match_snap_32_a_2_13","flipH":1}},"visualization":{"type":"furniture_animated","layerCount":1,"layers":{},"directions":{"2":{},"6":{}},"colors":{},"animations":{"0":{"layers":{"0":{"sequences":[[{"frame":0}]]}}},"1":{"layers":{"0":{"sequences":[[{"frame":0}]]}}},"100":{"transitionTo":1,"layers":{"0":{"sequences":[[{"frame":1},{"frame":2},{"frame":3},{"frame":4},{"frame":5},{"frame":6},{"frame":7},{"frame":8},{"frame":9},{"frame":10},{"frame":11},{"frame":12},{"frame":13},{"frame":14},{"frame":15},{"frame":16}]],"frameRepeat":2}}},"101":{"transitionTo":0,"layers":{"0":{"sequences":[[{"frame":1},{"frame":2},{"frame":3},{"frame":4},{"frame":5},{"frame":6},{"frame":7},{"frame":8},{"frame":9},{"frame":10},{"frame":11},{"frame":12},{"frame":13},{"frame":14},{"frame":15},{"frame":16}]],"frameRepeat":2}}}}},"logic":{"type":"furniture_multistate","dimensions":[1.0,1.0,0.65],"directions":[90,270],"particlesystems":[]}}