{"assets":{"xmas_c18_piano_64_sd_0_0":{"offsets":{"left":16,"top":8},"sprite":{"left":29,"top":0,"width":99,"height":50}},"xmas_c18_piano_64_a_0_0":{"offsets":{"left":19,"top":80},"sprite":{"left":128,"top":0,"width":54,"height":90}},"xmas_c18_piano_64_b_0_0":{"offsets":{"left":-1,"top":72},"sprite":{"left":74,"top":90,"width":74,"height":100}},"xmas_c18_piano_64_c_0_0":{"offsets":{"left":-48,"top":49},"sprite":{"left":0,"top":90,"width":37,"height":91}},"xmas_c18_piano_64_a_6_0":{"offsets":{"left":37,"top":79},"sprite":{"left":182,"top":0,"width":54,"height":90}},"xmas_c18_piano_64_b_6_0":{"offsets":{"left":77,"top":71},"sprite":{"left":148,"top":90,"width":74,"height":100}},"xmas_c18_piano_64_c_6_0":{"offsets":{"left":87,"top":48},"sprite":{"left":37,"top":90,"width":37,"height":91}},"xmas_c18_piano_icon_a":{"offsets":{"left":13,"top":14},"sprite":{"left":0,"top":0,"width":29,"height":32}},"xmas_c18_piano_64_sd_6_0":{"offsets":{"left":16,"top":8},"source":"xmas_c18_piano_64_sd_0_0","flipH":1}},"visualization":{"type":"furniture_static","layerCount":3,"layers":{"0":{},"1":{"z":"1000"},"2":{"z":"2000"}},"directions":{"0":{},"6":{}},"colors":{},"animations":{}},"logic":{"type":"furniture_basic","dimensions":[3.0,1.0,1.0],"directions":[0,270],"particlesystems":[]}}