{"assets":{"netari_carpet_64_a_0_0":{"offsets":{"left":161,"top":16},"sprite":{"left":131,"top":0,"width":262,"height":129}},"netari_carpet_64_a_2_0":{"offsets":{"left":161,"top":16},"source":"netari_carpet_64_a_0_0","flipH":1},"netari_carpet_icon_a":{"offsets":{"left":15,"top":7},"sprite":{"left":393,"top":0,"width":30,"height":15}},"netari_carpet_32_a_0_0":{"offsets":{"left":82,"top":8},"sprite":{"left":0,"top":0,"width":131,"height":64}},"netari_carpet_32_a_2_0":{"offsets":{"left":82,"top":8},"source":"netari_carpet_32_a_0_0","flipH":1}},"visualization":{"type":"furniture_static","layerCount":1,"layers":{"0":{"z":"-2000"}},"directions":{"0":{},"2":{}},"colors":{},"animations":{}},"logic":{"type":"furniture_basic","dimensions":[3.0,5.0,0.0],"directions":[0,90],"particlesystems":[]}}