{"h_std__2066__REGPOINTS":{"offset":"1,0"},"h_std_hr_2066__REGPOINTS":{"offset":"1,0"},"h_lsp_hrb_2067_2_0":{"offset":"-46,-123","left":"29","top":"16","width":"15","height":"15"},"h_lsp_hr_2067_2_0":{"offset":"-46,-123","left":"14","top":"16","width":"15","height":"15"},"sh_std__0__REGPOINTS":{"offset":"1,0"},"sh_std_hr_0__REGPOINTS":{"offset":"1,0"},"sh_std_hrb_2066_0_0":{"offset":"-7,39","link":"sh_std_hr_2066_0_0"},"sh_std_hr_2066_0_0":{"offset":"-7,39","left":"102","top":"32","width":"19","height":"17"},"sh_std_hrb_2066_1_0":{"offset":"-7,38","left":"92","top":"16","width":"16","height":"15"},"sh_std_hr_2066_1_0":{"offset":"-7,38","left":"61","top":"16","width":"16","height":"15"},"sh_std_hrb_2066_2_0":{"offset":"-6,38","left":"68","top":"32","width":"17","height":"17"},"sh_std_hr_2066_2_0":{"offset":"-6,38","left":"51","top":"32","width":"17","height":"17"},"sh_std_hrb_2066_3_0":{"offset":"-7,38","left":"0","top":"32","width":"17","height":"15"},"sh_std_hr_2066_3_0":{"offset":"-7,38","left":"108","top":"16","width":"17","height":"15"},"sh_std_hrb_2066_7_0":{"offset":"-8,39","link":"sh_std_hr_2066_7_0"},"sh_std_hr_2066_7_0":{"offset":"-8,39","left":"85","top":"32","width":"17","height":"18"},"sh_std_hrb_2067_0_0":{"offset":"-8,37","link":"sh_spk_hrb_2067_0_0"},"sh_std_hr_2067_0_0":{"offset":"-8,37","link":"sh_spk_hrb_2067_0_0"},"sh_std_hrb_2067_1_0":{"offset":"-8,36","left":"35","top":"0","width":"13","height":"12"},"sh_std_hr_2067_1_0":{"offset":"-8,36","left":"22","top":"0","width":"13","height":"12"},"sh_std_hrb_2067_2_0":{"offset":"-8,37","link":"sh_spk_hrb_2067_2_0"},"sh_std_hr_2067_2_0":{"offset":"-8,37","left":"0","top":"16","width":"14","height":"15"},"sh_std_hrb_2067_3_0":{"offset":"-8,36","link":"sh_spk_hrb_2066_3_0"},"sh_std_hr_2067_3_0":{"offset":"-8,36","link":"sh_spk_hr_2066_3_0"},"sh_std_hrb_2067_7_0":{"offset":"-9,38","link":"sh_std_hr_2067_7_0"},"sh_std_hr_2067_7_0":{"offset":"-9,38","left":"77","top":"16","width":"15","height":"16"},"sh_spk_hrb_2066_0_0":{"offset":"-7,39","link":"sh_std_hr_2066_0_0"},"sh_spk_hr_2066_0_0":{"offset":"-7,39","link":"sh_std_hr_2066_0_0"},"sh_spk_hrb_2066_1_0":{"offset":"-7,38","link":"sh_std_hrb_2066_1_0"},"sh_spk_hr_2066_1_0":{"offset":"-7,38","link":"sh_std_hr_2066_1_0"},"sh_spk_hrb_2066_2_0":{"offset":"-6,38","left":"34","top":"32","width":"17","height":"17"},"sh_spk_hr_2066_2_0":{"offset":"-6,38","left":"17","top":"32","width":"17","height":"17"},"sh_spk_hrb_2066_3_0":{"offset":"-8,36","left":"63","top":"0","width":"15","height":"12"},"sh_spk_hr_2066_3_0":{"offset":"-8,36","left":"48","top":"0","width":"15","height":"12"},"sh_spk_hrb_2066_7_0":{"offset":"-8,39","link":"sh_std_hr_2066_7_0"},"sh_spk_hr_2066_7_0":{"offset":"-8,39","link":"sh_std_hr_2066_7_0"},"sh_spk_hrb_2067_0_0":{"offset":"-8,37","left":"44","top":"16","width":"17","height":"14"},"sh_spk_hr_2067_0_0":{"offset":"-8,37","link":"sh_spk_hrb_2067_0_0"},"sh_spk_hrb_2067_1_0":{"offset":"-8,36","link":"sh_std_hrb_2067_1_0"},"sh_spk_hr_2067_1_0":{"offset":"-8,36","link":"sh_std_hr_2067_1_0"},"sh_spk_hrb_2067_2_0":{"offset":"-8,37","left":"104","top":"0","width":"14","height":"15"},"sh_spk_hr_2067_2_0":{"offset":"-8,37","link":"sh_std_hr_2067_2_0"},"sh_spk_hrb_2067_3_0":{"offset":"-8,36","link":"sh_spk_hrb_2066_3_0"},"sh_spk_hr_2067_3_0":{"offset":"-8,36","link":"sh_spk_hr_2066_3_0"},"sh_spk_hrb_2067_7_0":{"offset":"-9,38","link":"sh_std_hr_2067_7_0"},"sh_spk_hr_2067_7_0":{"offset":"-9,38","link":"sh_std_hr_2067_7_0"},"sh_lay_hrb_2066_2_0":{"offset":"12,20","link":"sh_lsp_hrb_2066_2_0"},"sh_lay_hr_2066_2_0":{"offset":"12,20","left":"78","top":"0","width":"13","height":"16"},"sh_lay_hrb_2067_2_0":{"offset":"11,19","left":"0","top":"0","width":"11","height":"14"},"sh_lay_hr_2067_2_0":{"offset":"11,19","link":"sh_lsp_hr_2067_2_0"},"sh_lsp_hrb_2066_2_0":{"offset":"-20,-60","left":"91","top":"0","width":"13","height":"16"},"sh_lsp_hr_2066_2_0":{"offset":"-20,-60","link":"sh_lay_hr_2066_2_0"},"sh_lsp_hrb_2067_2_0":{"offset":"-21,-61","link":"sh_lay_hrb_2067_2_0"},"sh_lsp_hr_2067_2_0":{"offset":"-21,-61","left":"11","top":"0","width":"11","height":"14"},"h_std__0__REGPOINTS":{"offset":"1,0"},"h_std_hr_0__REGPOINTS":{"offset":"1,0"},"h_std_hrb_2066_7_0":{"offset":"-18,77","left":"94","top":"193","width":"32","height":"36"},"h_std_hr_2066_7_0":{"offset":"-18,77","left":"62","top":"193","width":"32","height":"36"},"h_std_hrb_2066_0_0":{"offset":"-15,75","left":"35","top":"303","width":"35","height":"35"},"h_std_hr_2066_0_0":{"offset":"-15,75","left":"0","top":"303","width":"35","height":"35"},"h_std_hrb_2066_1_0":{"offset":"-13,76","left":"0","top":"267","width":"34","height":"35"},"h_std_hr_2066_1_0":{"offset":"-13,76","left":"64","top":"230","width":"34","height":"35"},"h_std_hrb_2066_2_0":{"offset":"-12,78","left":"40","top":"452","width":"40","height":"37"},"h_std_hr_2066_2_0":{"offset":"-12,78","left":"0","top":"452","width":"40","height":"37"},"h_std_hrb_2066_3_0":{"offset":"-12,79","left":"0","top":"490","width":"39","height":"38"},"h_std_hr_2066_3_0":{"offset":"-12,79","left":"80","top":"452","width":"39","height":"38"},"h_std_hrb_2067_7_0":{"offset":"-19,76","left":"30","top":"50","width":"30","height":"34"},"h_std_hr_2067_7_0":{"offset":"-19,76","left":"0","top":"50","width":"30","height":"34"},"h_std_hrb_2067_0_0":{"offset":"-16,74","left":"91","top":"50","width":"31","height":"33"},"h_std_hr_2067_0_0":{"offset":"-16,74","left":"60","top":"50","width":"31","height":"33"},"h_std_hrb_2067_1_0":{"offset":"-14,75","left":"94","top":"123","width":"32","height":"33"},"h_std_hr_2067_1_0":{"offset":"-14,75","left":"62","top":"123","width":"32","height":"33"},"h_std_hrb_2067_2_0":{"offset":"-13,77","left":"38","top":"380","width":"38","height":"34"},"h_std_hr_2067_2_0":{"offset":"-13,77","left":"0","top":"380","width":"38","height":"34"},"h_std_hrb_2067_3_0":{"offset":"-18,78","left":"95","top":"157","width":"31","height":"36"},"h_std_hr_2067_3_0":{"offset":"-18,78","left":"64","top":"157","width":"31","height":"36"},"h_spk_hrb_2066_7_0":{"offset":"-18,78","left":"32","top":"230","width":"32","height":"37"},"h_spk_hr_2066_7_0":{"offset":"-18,78","left":"0","top":"230","width":"32","height":"37"},"h_spk_hrb_2066_0_0":{"offset":"-15,76","left":"0","top":"339","width":"35","height":"36"},"h_spk_hr_2066_0_0":{"offset":"-15,76","left":"70","top":"303","width":"35","height":"36"},"h_spk_hrb_2066_1_0":{"offset":"-13,77","left":"68","top":"267","width":"34","height":"36"},"h_spk_hr_2066_1_0":{"offset":"-13,77","left":"34","top":"267","width":"34","height":"36"},"h_spk_hrb_2066_2_0":{"offset":"-12,78","left":"78","top":"415","width":"40","height":"37"},"h_spk_hr_2066_2_0":{"offset":"-12,78","left":"38","top":"415","width":"40","height":"37"},"h_spk_hrb_2066_3_0":{"offset":"-12,80","left":"78","top":"490","width":"39","height":"39"},"h_spk_hr_2066_3_0":{"offset":"-12,80","left":"39","top":"490","width":"39","height":"39"},"h_spk_hrb_2067_7_0":{"offset":"-19,77","left":"30","top":"84","width":"30","height":"35"},"h_spk_hr_2067_7_0":{"offset":"-19,77","left":"0","top":"84","width":"30","height":"35"},"h_spk_hrb_2067_0_0":{"offset":"-16,75","left":"31","top":"123","width":"31","height":"34"},"h_spk_hr_2067_0_0":{"offset":"-16,75","left":"0","top":"123","width":"31","height":"34"},"h_spk_hrb_2067_1_0":{"offset":"-14,76","left":"32","top":"157","width":"32","height":"34"},"h_spk_hr_2067_1_0":{"offset":"-14,76","left":"0","top":"157","width":"32","height":"34"},"h_spk_hrb_2067_2_0":{"offset":"-13,78","left":"0","top":"415","width":"38","height":"35"},"h_spk_hr_2067_2_0":{"offset":"-13,78","left":"76","top":"380","width":"38","height":"35"},"h_spk_hrb_2067_3_0":{"offset":"-18,79","left":"31","top":"193","width":"31","height":"37"},"h_spk_hr_2067_3_0":{"offset":"-18,79","left":"0","top":"193","width":"31","height":"37"},"h_lay_hrb_2066_2_0":{"offset":"23,43","left":"66","top":"339","width":"31","height":"41"},"h_lay_hr_2066_2_0":{"offset":"23,43","left":"35","top":"339","width":"31","height":"41"},"h_lay_hrb_2067_2_0":{"offset":"22,42","left":"87","top":"84","width":"27","height":"39"},"h_lay_hr_2067_2_0":{"offset":"22,42","left":"60","top":"84","width":"27","height":"39"},"h_lsp_hrb_2066_2_0":{"offset":"-41,-117","link":"h_lay_hrb_2066_2_0"},"h_lsp_hr_2066_2_0":{"offset":"-41,-117","link":"h_lay_hr_2066_2_0"},"manifest":{},"hair_F_neat":{}}